Workbook

Sheet Top Redes
B1: TOP REDES | D1: META REDES | E1: META TOPS | F1: Realizado R$ | G1: % REDES | H1: % TOPS | I1: A Faturar R$ | J1: Faltando R$ | K1: %Fat + a Faturar REDES | L1: %Fat + a Fat TOPS | M1: Última atualização
B2: JULHO | D2: =SUBTOTAL(9,D4:D29) -> 3500696.6 | E2: =SUBTOTAL(9,E4:E29) -> 2569994.7 | F2: =SUBTOTAL(9,F4:F29) -> 3538158.9 | G2: =IFERROR(F2/D2,0) -> 1.0107014 | H2: =IFERROR(F2/E2,0) -> 1.3767184 | I2: =SUBTOTAL(9,I4:I23) -> 270973.56 | J2: =SUBTOTAL(9,J4:J29) -> 484199.8 | K2: =(F2+I2)/D2 -> 1.088107 | L2: =(F2+I2)/E2 -> 1.4821558 | M2: 46239.358
A3: REDE | B3: EQUIPE | C3: CÓD RCA | D3: META REDES | E3: META TOPS | F3: REALIZADO | G3: % REDES | H3: % TOPS | I3: A Faturar R$ | J3: Falta GAP | K3: Real + A Faturar | L3: Real + A Faturar
A4: REDE ABV | B4: 906 | C4: 507 | D4: 884542.96 | E4: 950000 | F4: =SUMIFS(redes!$F:$F,redes!$D:$D,'Top Redes'!A4) -> 1095922.4 | G4: =IFERROR(F4/D4,0) -> 1.2389702 | H4: =IFERROR(F4/E4,0) -> 1.1536025 | I4: =SUMIFS(redes!$G:$G,redes!$D:$D,'Top Redes'!A4) -> 178.56 | J4: =IF(D4-F4-I4<=0,0,D4-F4-I4) -> 0 | K4: =IFERROR((F4+I4)/E4,0) -> 1.1537905 | L4: =IFERROR((F4+I4)/D4,0) -> 1.2391721
A5: REDE VRA / MEGA | B5: 906 | C5: 721 | D5: 624018.3 | E5: 566915.45 | F5: =SUMIFS(redes!$F:$F,redes!$D:$D,'Top Redes'!A5) -> 579604.12 | G5: =IFERROR(F5/D5,0) -> 0.92882551 | H5: =IFERROR(F5/E5,0) -> 1.0223819 | I5: =SUMIFS(redes!$G:$G,redes!$D:$D,'Top Redes'!A5) -> 1607.04 | J5: =IF(D5-F5-I5<=0,0,D5-F5-I5) -> 42807.142 | K5: =IFERROR((F5+I5)/E5,0) -> 1.0252167 | L5: =IFERROR((F5+I5)/D5,0) -> 0.93140082
A6: REDE PIRES | B6: 906 | C6: 202 | D6: 406248.89 | E6: 106400.08 | F6: =SUMIFS(redes!$F:$F,redes!$D:$D,'Top Redes'!A6) -> 328342.09 | G6: =IFERROR(F6/D6,0) -> 0.8082289 | H6: =IFERROR(F6/E6,0) -> 3.0859196 | I6: =SUMIFS(redes!$G:$G,redes!$D:$D,'Top Redes'!A6) -> 0 | J6: =IF(D6-F6-I6<=0,0,D6-F6-I6) -> 77906.797 | K6: =IFERROR((F6+I6)/E6,0) -> 3.0859196 | L6: =IFERROR((F6+I6)/D6,0) -> 0.8082289
A7: REDE CIDADE BRANCA (QUADRI) | B7: 902 | C7: 714 | D7: 132472.23 | E7: 149533.32 | F7: =SUMIFS(redes!$F:$F,redes!$D:$D,'Top Redes'!A7) -> 76993.12 | G7: =IFERROR(F7/D7,0) -> 0.58120198 | H7: =IFERROR(F7/E7,0) -> 0.51488939 | I7: =SUMIFS(redes!$G:$G,redes!$D:$D,'Top Redes'!A7) -> 0 | J7: =IF(D7-F7-I7<=0,0,D7-F7-I7) -> 55479.106 | K7: =IFERROR((F7+I7)/E7,0) -> 0.51488939 | L7: =IFERROR((F7+I7)/D7,0) -> 0.58120198
A8: REDE NOVA ESTRELA | B8: 906 | C8: 211 | D8: 335377.66 | E8: 209584.19 | F8: =SUMIFS(redes!$F:$F,redes!$D:$D,'Top Redes'!A8) -> 234458.93 | G8: =IFERROR(F8/D8,0) -> 0.69908929 | H8: =IFERROR(F8/E8,0) -> 1.1186862 | I8: =SUMIFS(redes!$G:$G,redes!$D:$D,'Top Redes'!A8) -> 714.24 | J8: =IF(D8-F8-I8<=0,0,D8-F8-I8) -> 100204.49 | K8: =IFERROR((F8+I8)/E8,0) -> 1.1220941 | L8: =IFERROR((F8+I8)/D8,0) -> 0.70121895
A9: REDE SOL - ANDRE RICARDO | B9: 906 | C9: 507 | D9: 160890.06 | E9: 137621.69 | F9: =SUMIFS(redes!$F:$F,redes!$D:$D,'Top Redes'!A9) -> 218408.82 | G9: =IFERROR(F9/D9,0) -> 1.3575035 | H9: =IFERROR(F9/E9,0) -> 1.5870233 | I9: =SUMIFS(redes!$G:$G,redes!$D:$D,'Top Redes'!A9) -> 5986.12 | J9: =IF(D9-F9-I9<=0,0,D9-F9-I9) -> 0 | K9: =IFERROR((F9+I9)/E9,0) -> 1.6305202 | L9: =IFERROR((F9+I9)/D9,0) -> 1.3947098
A10: REDE NUNES | B10: 906 | C10: 702 | D10: 81473.54 | E10: 76001.987 | F10: =SUMIFS(redes!$F:$F,redes!$D:$D,'Top Redes'!A10) -> 114704.09 | G10: =IFERROR(F10/D10,0) -> 1.4078692 | H10: =IFERROR(F10/E10,0) -> 1.5092249 | I10: =SUMIFS(redes!$G:$G,redes!$D:$D,'Top Redes'!A10) -> 35827.92 | J10: =IF(D10-F10-I10<=0,0,D10-F10-I10) -> 0 | K10: =IFERROR((F10+I10)/E10,0) -> 1.9806326 | L10: =IFERROR((F10+I10)/D10,0) -> 1.8476184
A11: REDE DAMASCENO-PORTAL/PRINCESA | B11: 902 | C11: 703 | D11: 119452.2 | E11: 37318.624 | F11: =SUMIFS(redes!$F:$F,redes!$D:$D,'Top Redes'!A11) -> 136574.5 | G11: =IFERROR(F11/D11,0) -> 1.1433401 | H11: =IFERROR(F11/E11,0) -> 3.6596874 | I11: =SUMIFS(redes!$G:$G,redes!$D:$D,'Top Redes'!A11) -> 42877.97 | J11: =IF(D11-F11-I11<=0,0,D11-F11-I11) -> 0 | K11: =IFERROR((F11+I11)/E11,0) -> 4.8086571 | L11: =IFERROR((F11+I11)/D11,0) -> 1.5022952
A12: REDE JCHAGAS - FOGO/CHAMA | B12: 910 | C12: 718 | D12: 58236.697 | E12: 0 | F12: =SUMIFS(redes!$F:$F,redes!$D:$D,'Top Redes'!A12) -> 131593.66 | G12: =IFERROR(F12/D12,0) -> 2.2596347 | H12: =IFERROR(F12/E12,0) -> 0 | I12: =SUMIFS(redes!$G:$G,redes!$D:$D,'Top Redes'!A12) -> 150067.11 | J12: =IF(D12-F12-I12<=0,0,D12-F12-I12) -> 0 | K12: =IFERROR((F12+I12)/E12,0) -> 0 | L12: =IFERROR((F12+I12)/D12,0) -> 4.8364826
A13: REDEMS UNIBEM | B13: 902 | C13: 708 | D13: 52298.332 | E13: 52781.349 | F13: =SUMIFS(redes!$F:$F,redes!$D:$D,'Top Redes'!A13) -> 54084.81 | G13: =IFERROR(F13/D13,0) -> 1.0341594 | H13: =IFERROR(F13/E13,0) -> 1.0246955 | I13: =SUMIFS(redes!$G:$G,redes!$D:$D,'Top Redes'!A13) -> 2443.72 | J13: =IF(D13-F13-I13<=0,0,D13-F13-I13) -> 0 | K13: =IFERROR((F13+I13)/E13,0) -> 1.0709944 | L13: =IFERROR((F13+I13)/D13,0) -> 1.0808859
A14: REDE SUPER VALE | B14: 902 | C14: 709 | D14: 47842.231 | E14: 0 | F14: =SUMIFS(redes!$F:$F,redes!$D:$D,'Top Redes'!A14) -> 0 | G14: =IFERROR(F14/D14,0) -> 0 | H14: =IFERROR(F14/E14,0) -> 0 | I14: =SUMIFS(redes!$G:$G,redes!$D:$D,'Top Redes'!A14) -> 0 | J14: =IF(D14-F14-I14<=0,0,D14-F14-I14) -> 47842.231 | K14: =IFERROR((F14+I14)/E14,0) -> 0 | L14: =IFERROR((F14+I14)/D14,0) -> 0
A15: REDE ATLANTICO | B15: 902 | C15: 703 | D15: 53050.67 | E15: 51861.46 | F15: =SUMIFS(redes!$F:$F,redes!$D:$D,'Top Redes'!A15) -> 69939.55 | G15: =IFERROR(F15/D15,0) -> 1.3183537 | H15: =IFERROR(F15/E15,0) -> 1.3485843 | I15: =SUMIFS(redes!$G:$G,redes!$D:$D,'Top Redes'!A15) -> 29397.13 | J15: =IF(D15-F15-I15<=0,0,D15-F15-I15) -> 0 | K15: =IFERROR((F15+I15)/E15,0) -> 1.9154239 | L15: =IFERROR((F15+I15)/D15,0) -> 1.8724868
... A25: REDE MACAUBA | B25: 910 | C25: 704 | D25: 56115.084 | E25: 50653.305 | F25: =SUMIFS(redes!$F:$F,redes!$D:$D,'Top Redes'!A25) -> 29843.55 | G25: =IFERROR(F25/D25,0) -> 0.5318276 | H25: =IFERROR(F25/E25,0) -> 0.58917281 | I25: =SUMIFS(redes!$G:$G,redes!$D:$D,'Top Redes'!A25) -> 0 | J25: =IF(D25-F25-I25<=0,0,D25-F25-I25) -> 26271.534 | K25: =IFERROR((F25+I25)/E25,0) -> 0.58917281 | L25: =IFERROR((F25+I25)/D25,0) -> 0.5318276

Sheet 12.326
A1: PEDIDO.SETOR | B1: PEDIDO | C1: RAZÃO | D1: CNPJ | E1: MARGEM | F1: CFOP | G1: PORTADOR | H1: LISTA | I1: SALDO DMC | J1: TROCAS | K1: TOTAL PEDIDO | L1: PRAZOS | M1: SITUAÇÃO | N1: DIG IMP | O1: PROGRAMADO | P1: P.BRUTO | Q1: SETOR | R1: USUARIO | S1: REG | T1: QTD CX | U1: CIDADE | V1: MOV
A2: =OFFSET(hoje12_326_sp8,1,1,1,1)&"."&OFFSET(hoje12_326_sp8,1,16,1,1) -> 1067.135 | B2: 1067 | C2: CORREA MERC E COM VAR | D2: 7691695000144 | E2: 32,29 | F2: 51234 | G2: BANCO ITAU | H2: 08 | I2: 5,14- | J2: 0,00 | K2: 451.56 | L2: 007 014 000 | M2: ***** | N2: 23/07/26 | O2: 30/07/26 | P2: 38,36 | Q2: 135 | R2: kuba | S2: 002 | T2: 00071 | U2: CAMPO GRANDE | V2: I
A3: =OFFSET(hoje12_326_sp8,2,1,1,1)&"."&OFFSET(hoje12_326_sp8,2,16,1,1) -> 211001.211 | B3: 211001 | C3: NOVA ESTRELA COM DE A | D3: 12887219000303 | E3: 30,46 | F3: 51201 | G3: BANCO ITAU | H3: 08 | I3: 0,00 | J3: 0,00 | K3: 178.56 | L3: 035 000 000 | M3: 2-LIB | N3: 29/07/26 | O3: 30/07/26 | P3: 2,37 | Q3: 211 | R3: vinicius | S3: 305 | T3: 00012 | U3: TRES LAGOAS | V3: A
A4: =OFFSET(hoje12_326_sp8,3,1,1,1)&"."&OFFSET(hoje12_326_sp8,3,16,1,1) -> 211002.211 | B4: 211002 | C4: NOVA ESTRELA COMERCIO | D4: 12887219000567 | E4: 30,46 | F4: 51201 | G4: BANCO ITAU | H4: 08 | I4: 0,00 | J4: 0,00 | K4: 178.56 | L4: 035 000 000 | M4: 2-LIB | N4: 29/07/26 | O4: 30/07/26 | P4: 2,37 | Q4: 211 | R4: vinicius | S4: 306 | T4: 00012 | U4: TRES LAGOAS | V4: A
A5: =OFFSET(hoje12_326_sp8,4,1,1,1)&"."&OFFSET(hoje12_326_sp8,4,16,1,1) -> 211003.211 | B5: 211003 | C5: NOVA ESTRELA COM DE A | D5: 12887219000214 | E5: 30,46 | F5: 51201 | G5: BANCO ITAU | H5: 08 | I5: 0,00 | J5: 0,00 | K5: 178.56 | L5: 035 000 000 | M5: 2-LIB | N5: 29/07/26 | O5: 30/07/26 | P5: 2,37 | Q5: 211 | R5: vinicius | S5: 304 | T5: 00012 | U5: TRES LAGOAS | V5: A
A6: =OFFSET(hoje12_326_sp8,5,1,1,1)&"."&OFFSET(hoje12_326_sp8,5,16,1,1) -> 211004.211 | B6: 211004 | C6: NOVA ESTRELA COM DE A | D6: 12887219000133 | E6: 30,46 | F6: 51201 | G6: BANCO ITAU | H6: 08 | I6: 0,00 | J6: 0,00 | K6: 178.56 | L6: 035 000 000 | M6: 2-LIB | N6: 29/07/26 | O6: 30/07/26 | P6: 2,37 | Q6: 211 | R6: vinicius | S6: 303 | T6: 00012 | U6: TRES LAGOAS | V6: A
A7: =OFFSET(hoje12_326_sp8,6,1,1,1)&"."&OFFSET(hoje12_326_sp8,6,16,1,1) -> 600.507 | B7: 600 | C7: A R S SUPERMERCADOS L | D7: 20335148000275 | E7: 25,22 | F7: 51201 | G7: BANCO ITAU | H7: 08 | I7: 38,74- | J7: 0,00 | K7: 2814.5 | L7: 028 035 042 | M7: 2-LIB | N7: 30/07/26 | O7: 30/07/26 | P7: 34,41 | Q7: 507 | R7: kuba | S7: 320 | T7: 00204 | U7: PONTA PORA | V7: A
A8: =OFFSET(hoje12_326_sp8,7,1,1,1)&"."&OFFSET(hoje12_326_sp8,7,16,1,1) -> 601.507 | B8: 601 | C8: A R S SUPERMERCADOS L | D8: 20335148000194 | E8: 25,22 | F8: 51201 | G8: BANCO ITAU | H8: 08 | I8: 38,74- | J8: 0,00 | K8: 2814.5 | L8: 028 035 042 | M8: 2-LIB | N8: 30/07/26 | O8: 30/07/26 | P8: 34,41 | Q8: 507 | R8: kuba | S8: 320 | T8: 00204 | U8: PONTA PORA | V8: A
A9: =OFFSET(hoje12_326_sp8,8,1,1,1)&"."&OFFSET(hoje12_326_sp8,8,16,1,1) -> 507001.507 | B9: 507001 | C9: A R S SUPERMERCADOS L | D9: 20335148000194 | E9: 30,46 | F9: 51201 | G9: BANCO ITAU | H9: 08 | I9: 0,00 | J9: 0,00 | K9: 178.56 | L9: 035 000 000 | M9: 2-LIB | N9: 29/07/26 | O9: 30/07/26 | P9: 2,37 | Q9: 507 | R9: vinicius | S9: 320 | T9: 00012 | U9: PONTA PORA | V9: A
A10: =OFFSET(hoje12_326_sp8,9,1,1,1)&"."&OFFSET(hoje12_326_sp8,9,16,1,1) -> 507002.507 | B10: 507002 | C10: A R S SUPERMERCADOS L | D10: 20335148000275 | E10: 30,46 | F10: 51201 | G10: BANCO ITAU | H10: 08 | I10: 0,00 | J10: 0,00 | K10: 178.56 | L10: 035 000 000 | M10: 2-LIB | N10: 29/07/26 | O10: 30/07/26 | P10: 2,37 | Q10: 507 | R10: vinicius | S10: 320 | T10: 00012 | U10: PONTA PORA | V10: A
A11: =OFFSET(hoje12_326_sp8,10,1,1,1)&"."&OFFSET(hoje12_326_sp8,10,16,1,1) -> 507003.507 | B11: 507003 | C11: CD-00 ABV COMERCIO DE | D11: 4757459000519 | E11: 30,46 | F11: 51201 | G11: BANCO ITAU | H11: 08 | I11: 0,00 | J11: 0,00 | K11: 178.56 | L11: 039 000 000 | M11: 2-LIB | N11: 29/07/26 | O11: 30/07/26 | P11: 2,37 | Q11: 507 | R11: vinicius | S11: 336 | T11: 00012 | U11: DOURADOS | V11: A
A12: =OFFSET(hoje12_326_sp8,11,1,1,1)&"."&OFFSET(hoje12_326_sp8,11,16,1,1) -> 1240.702 | B12: 1240 | C12: SUPERMERCADO GAUCHAO | D12: 35831943000140 | E12: 22,07 | F12: 51201 | G12: BANCO ITAU | H12: 08 | I12: 43,02- | J12: 0,00 | K12: 790.72 | L12: 028 000 000 | M12: 2-LIB | N12: 30/07/26 | O12: 30/07/26 | P12: 16,60 | Q12: 702 | R12: willian | S12: 418 | T12: 00077 | U12: CAMPO GRANDE | V12: A
A13: =OFFSET(hoje12_326_sp8,12,1,1,1)&"."&OFFSET(hoje12_326_sp8,12,16,1,1) -> 1241.702 | B13: 1241 | C13: SUPERMERCADO GAUCHAO | D13: 35831943000302 | E13: 22,07 | F13: 51201 | G13: BANCO ITAU | H13: 08 | I13: 43,02- | J13: 0,00 | K13: 790.72 | L13: 028 000 000 | M13: 2-LIB | N13: 30/07/26 | O13: 30/07/26 | P13: 16,60 | Q13: 702 | R13: willian | S13: 418 | T13: 00077 | U13: CAMPO GRANDE | V13: A
A14: =OFFSET(hoje12_326_sp8,13,1,1,1)&"."&OFFSET(hoje12_326_sp8,13,16,1,1) -> 1242.702 | B14: 1242 | C14: SUPERMERCADO GAUCHAO | D14: 35831943000493 | E14: 22,07 | F14: 51201 | G14: BANCO ITAU | H14: 08 | I14: 43,02- | J14: 0,00 | K14: 790.72 | L14: 028 000 000 | M14: 2-LIB | N14: 30/07/26 | O14: 30/07/26 | P14: 16,60 | Q14: 702 | R14: willian | S14: 038 | T14: 00077 | U14: SIDROLANDIA | V14: A
A15: =OFFSET(hoje12_326_sp8,14,1,1,1)&"."&OFFSET(hoje12_326_sp8,14,16,1,1) -> 1243.702 | B15: 1243 | C15: SUPERMERCADO GAUCHAO | D15: 35831943000574 | E15: 22,07 | F15: 51201 | G15: BANCO ITAU | H15: 08 | I15: 43,02- | J15: 0,00 | K15: 790.72 | L15: 028 000 000 | M15: 2-LIB | N15: 30/07/26 | O15: 30/07/26 | P15: 16,60 | Q15: 702 | R15: willian | S15: 008 | T15: 00077 | U15: CAMPO GRANDE | V15: A
A16: =OFFSET(hoje12_326_sp8,15,1,1,1)&"."&OFFSET(hoje12_326_sp8,15,16,1,1) -> 1244.702 | B16: 1244 | C16: SUPERMERCADO GAUCHAO | D16: 35831943000736 | E16: 21,86 | F16: 51201 | G16: BANCO ITAU | H16: 08 | I16: 43,02- | J16: 0,00 | K16: 665.32 | L16: 028 000 000 | M16: 2-LIB | N16: 30/07/26 | O16: 30/07/26 | P16: 15,29 | Q16: 702 | R16: willian | S16: 002 | T16: 00065 | U16: CAMPO GRANDE | V16: A
A17: =OFFSET(hoje12_326_sp8,16,1,1,1)&"."&OFFSET(hoje12_326_sp8,16,16,1,1) -> 1245.702 | B17: 1245 | C17: SUPERMERCADO GAUCHAO | D17: 35831943000906 | E17: 22,30 | F17: 51201 | G17: BANCO ITAU | H17: 01 | I17: 43,02- | J17: 0,00 | K17: 853.6 | L17: 028 000 000 | M17: 2-LIB | N17: 30/07/26 | O17: 30/07/26 | P17: 16,75 | Q17: 702 | R17: willian | S17: 041 | T17: 00080 | U17: SONORA | V17: A
A18: =OFFSET(hoje12_326_sp8,17,1,1,1)&"."&OFFSET(hoje12_326_sp8,17,16,1,1) -> 1246.702 | B18: 1246 | C18: SUPERMERCADO GAUCHAO | D18: 35831943000221 | E18: 22,30 | F18: 51201 | G18: BANCO ITAU | H18: 08 | I18: 43,02- | J18: 0,00 | K18: 853.6 | L18: 028 000 000 | M18: 2-LIB | N18: 30/07/26 | O18: 30/07/26 | P18: 16,75 | Q18: 702 | R18: willian | S18: 036 | T18: 00080 | U18: NOVA ALVORADA DO SUL | V18: A
A19: =OFFSET(hoje12_326_sp8,18,1,1,1)&"."&OFFSET(hoje12_326_sp8,18,16,1,1) -> 1247.702 | B19: 1247 | C19: OLIVEIRA E CARNEIRO L | D19: 9531413001815 | E19: 24,79 | F19: 51201 | G19: BANCO ITAU | H19: 05 | I19: 2.084,44- | J19: 0,00 | K19: 52378.94 | L19: 049 000 000 | M19: 1-BLO | N19: 30/07/26 | O19: 30/07/26 | P19: 1.514,25 | Q19: 702 | R19: kuba | S19: 034 | T19: 07662 | U19: CORUMBA | V19: A
A20: =OFFSET(hoje12_326_sp8,19,1,1,1)&"."&OFFSET(hoje12_326_sp8,19,16,1,1) -> 1248.702 | B20: 1248 | C20: OLIVEIRA E CARNEIRO L | D20: 9531413000339 | E20: 26,47 | F20: 51201 | G20: BANCO ITAU | H20: 08 | I20: 608,21- | J20: 0,00 | K20: 10134.23 | L20: 035 000 000 | M20: 1-BLO | N20: 30/07/26 | O20: 30/07/26 | P20: 290,10 | Q20: 702 | R20: kuba | S20: 428 | T20: 01995 | U20: CAMPO GRANDE | V20: A
A21: =OFFSET(hoje12_326_sp8,20,1,1,1)&"."&OFFSET(hoje12_326_sp8,20,16,1,1) -> 1249.702 | B21: 1249 | C21: OLIVEIRA E CARNEIRO L | D21: 9531413001491 | E21: 27,15 | F21: 51201 | G21: BANCO ITAU | H21: 08 | I21: 125,73- | J21: 0,00 | K21: 3860.85 | L21: 035 000 000 | M21: 2-LIB | N21: 30/07/26 | O21: 30/07/26 | P21: 140,11 | Q21: 702 | R21: kuba | S21: 002 | T21: 00640 | U21: CAMPO GRANDE | V21: A
A22: =OFFSET(hoje12_326_sp8,21,1,1,1)&"."&OFFSET(hoje12_326_sp8,21,16,1,1) -> 1250.702 | B22: 1250 | C22: OLIVEIRA E CARNEIRO L | D22: 9531413001068 | E22: 27,17 | F22: 51201 | G22: BANCO ITAU | H22: 08 | I22: 109,85- | J22: 0,00 | K22: 3621.15 | L22: 035 000 000 | M22: 1-BLO | N22: 30/07/26 | O22: 30/07/26 | P22: 96,36 | Q22: 702 | R22: kuba | S22: 413 | T22: 00566 | U22: TERENOS | V22: A
A23: =OFFSET(hoje12_326_sp8,22,1,1,1)&"."&OFFSET(hoje12_326_sp8,22,16,1,1) -> 1251.702 | B23: 1251 | C23: OLIVEIRA E CARNEIRO L | D23: 9531413000258 | E23: 24,05 | F23: 51201 | G23: BANCO ITAU | H23: 08 | I23: 90,48- | J23: 0,00 | K23: 1207.44 | L23: 035 000 000 | M23: 1-BLO | N23: 30/07/26 | O23: 30/07/26 | P23: 36,08 | Q23: 702 | R23: kuba | S23: 004 | T23: 00262 | U23: CAMPO GRANDE | V23: A
A24: =OFFSET(hoje12_326_sp8,23,1,1,1)&"."&OFFSET(hoje12_326_sp8,23,16,1,1) -> 1252.702 | B24: 1252 | C24: OLIVEIRA E CARNEIRO L | D24: 9531413000762 | E24: 25,07 | F24: 51201 | G24: BANCO ITAU | H24: 08 | I24: 221,42- | J24: 0,00 | K24: 3681.46 | L24: 035 000 000 | M24: 1-BLO | N24: 30/07/26 | O24: 30/07/26 | P24: 108,98 | Q24: 702 | R24: kuba | S24: 004 | T24: 00639 | U24: CAMPO GRANDE | V24: A
A25: =OFFSET(hoje12_326_sp8,24,1,1,1)&"."&OFFSET(hoje12_326_sp8,24,16,1,1) -> 1254.702 | B25: 1254 | C25: OLIVEIRA E CARNEIRO L | D25: 9531413000681 | E25: 30,28 | F25: 51201 | G25: BANCO ITAU | H25: 08 | I25: 19,54- | J25: 0,00 | K25: 1102.68 | L25: 035 000 000 | M25: 1-BLO | N25: 30/07/26 | O25: 30/07/26 | P25: 20,53 | Q25: 702 | R25: kuba | S25: 006 | T25: 00152 | U25: CAMPO GRANDE | V25: A
A26: =OFFSET(hoje12_326_sp8,25,1,1,1)&"."&OFFSET(hoje12_326_sp8,25,16,1,1) -> 1255.702 | B26: 1255 | C26: OLIVEIRA E CARNEIRO L | D26: 9531413001220 | E26: 24,95 | F26: 51201 | G26: BANCO ITAU | H26: 08 | I26: 164,38- | J26: 0,00 | K26: 2215.04 | L26: 035 000 000 | M26: 2-LIB | N26: 30/07/26 | O26: 30/07/26 | P26: 50,04 | Q26: 702 | R26: kuba | S26: 427 | T26: 00382 | U26: CAMPO GRANDE | V26: A
A27: =OFFSET(hoje12_326_sp8,26,1,1,1)&"."&OFFSET(hoje12_326_sp8,26,16,1,1) -> 1256.702 | B27: 1256 | C27: OLIVEIRA E CARNEIRO L | D27: 9531413001300 | E27: 28,54 | F27: 51201 | G27: BANCO ITAU | H27: 08 | I27: 85,52- | J27: 0,00 | K27: 4175.43 | L27: 035 000 000 | M27: 1-BLO | N27: 30/07/26 | O27: 30/07/26 | P27: 107,34 | Q27: 702 | R27: kuba | S27: 010 | T27: 00539 | U27: CAMPO GRANDE | V27: A
A28: =OFFSET(hoje12_326_sp8,27,1,1,1)&"."&OFFSET(hoje12_326_sp8,27,16,1,1) -> 1257.702 | B28: 1257 | C28: OLIVEIRA E CARNEIRO L | D28: 9531413000177 | E28: 26,66 | F28: 51201 | G28: BANCO ITAU | H28: 08 | I28: 175,48- | J28: 0,00 | K28: 3000.47 | L28: 035 000 000 | M28: 1-BLO | N28: 30/07/26 | O28: 30/07/26 | P28: 95,10 | Q28: 702 | R28: kuba | S28: 004 | T28: 00687 | U28: CAMPO GRANDE | V28: A
A29: =OFFSET(hoje12_326_sp8,28,1,1,1)&"."&OFFSET(hoje12_326_sp8,28,16,1,1) -> 1258.702 | B29: 1258 | C29: OLIVEIRA E CARNEIRO L | D29: 9531413000410 | E29: 25,81 | F29: 51201 | G29: BANCO ITAU | H29: 08 | I29: 161,16- | J29: 0,00 | K29: 2829.17 | L29: 035 000 000 | M29: 1-BLO | N29: 30/07/26 | O29: 30/07/26 | P29: 84,90 | Q29: 702 | R29: kuba | S29: 010 | T29: 00505 | U29: CAMPO GRANDE | V29: A
A30: =OFFSET(hoje12_326_sp8,29,1,1,1)&"."&OFFSET(hoje12_326_sp8,29,16,1,1) -> 702001.702 | B30: 702001 | C30: SUPERMERCADO GAUCHAO | D30: 35831943000655 | E30: 30,46 | F30: 51201 | G30: BANCO ITAU | H30: 08 | I30: 0,00 | J30: 0,00 | K30: 178.56 | L30: 028 000 000 | M30: 2-LIB | N30: 29/07/26 | O30: 30/07/26 | P30: 2,37 | Q30: 702 | R30: vinicius | S30: 418 | T30: 00012 | U30: CAMPO GRANDE | V30: A
A31: =OFFSET(hoje12_326_sp8,30,1,1,1)&"."&OFFSET(hoje12_326_sp8,30,16,1,1) -> 2406.703 | B31: 2406 | C31: DAMASCENO E DAMASCENO | D31: 1274396000390 | E31: 14,36 | F31: 51201 | G31: BANCO ITAU | H31: 08 | I31: 337,76- | J31: 0,00 | K31: 2092.12 | L31: 028 000 000 | M31: 2-LIB | N31: 23/07/26 | O31: 30/07/26 | P31: 79,34 | Q31: 703 | R31: willian | S31: 330 | T31: 00204 | U31: AQUIDAUANA | V31: A
A32: =OFFSET(hoje12_326_sp8,31,1,1,1)&"."&OFFSET(hoje12_326_sp8,31,16,1,1) -> 2407.703 | B32: 2407 | C32: DAMASCENO E DAMASCENO | D32: 1274396000209 | E32: 14,47 | F32: 51201 | G32: BANCO ITAU | H32: 08 | I32: 367,71- | J32: 0,00 | K32: 2261.91 | L32: 028 000 000 | M32: 2-LIB | N32: 23/07/26 | O32: 30/07/26 | P32: 85,20 | Q32: 703 | R32: willian | S32: 330 | T32: 00243 | U32: ANASTACIO | V32: A
A33: =OFFSET(hoje12_326_sp8,32,1,1,1)&"."&OFFSET(hoje12_326_sp8,32,16,1,1) -> 2408.703 | B33: 2408 | C33: DAMASCENO E DAMASCENO | D33: 1274396000632 | E33: 11,01 | F33: 51201 | G33: BANCO ITAU | H33: 08 | I33: 1.009,96- | J33: 0,00 | K33: 5755.34 | L33: 028 000 000 | M33: 2-LIB | N33: 23/07/26 | O33: 30/07/26 | P33: 259,14 | Q33: 703 | R33: willian | S33: 330 | T33: 00666 | U33: ANASTACIO | V33: A
A34: =OFFSET(hoje12_326_sp8,33,1,1,1)&"."&OFFSET(hoje12_326_sp8,33,16,1,1) -> 2409.703 | B34: 2409 | C34: DAMASCENO E DAMASCENO | D34: 1274396000713 | E34: 14,90 | F34: 51201 | G34: BANCO ITAU | H34: 08 | I34: 300,15- | J34: 0,00 | K34: 1878.93 | L34: 028 000 000 | M34: 2-LIB | N34: 23/07/26 | O34: 30/07/26 | P34: 76,73 | Q34: 703 | R34: willian | S34: 331 | T34: 00180 | U34: MIRANDA | V34: A
A35: =OFFSET(hoje12_326_sp8,34,1,1,1)&"."&OFFSET(hoje12_326_sp8,34,16,1,1) -> 2410.703 | B35: 2410 | C35: DAMASCENO E DAMASCENO | D35: 1274396000802 | E35: 14,48 | F35: 51201 | G35: BANCO ITAU | H35: 08 | I35: 372,60- | J35: 0,00 | K35: 2248.86 | L35: 028 000 000 | M35: 2-LIB | N35: 23/07/26 | O35: 30/07/26 | P35: 88,57 | Q35: 703 | R35: willian | S35: 039 | T35: 00267 | U35: CHAPADAO DO SUL | V35: A
A36: =OFFSET(hoje12_326_sp8,35,1,1,1)&"."&OFFSET(hoje12_326_sp8,35,16,1,1) -> 2412.703 | B36: 2412 | C36: DAMASCENO E DAMASCENO | D36: 1274396001019 | E36: 11,77 | F36: 51201 | G36: BANCO ITAU | H36: 08 | I36: 668,89- | J36: 0,00 | K36: 3849.11 | L36: 028 000 000 | M36: 2-LIB | N36: 23/07/26 | O36: 30/07/26 | P36: 179,74 | Q36: 703 | R36: willian | S36: 330 | T36: 00432 | U36: AQUIDAUANA | V36: A
A37: =OFFSET(hoje12_326_sp8,36,1,1,1)&"."&OFFSET(hoje12_326_sp8,36,16,1,1) -> 2413.703 | B37: 2413 | C37: DAMASCENO E DAMASCENO | D37: 1274396000985 | E37: 12,18 | F37: 51201 | G37: BANCO ITAU | H37: 08 | I37: 618,42- | J37: 0,00 | K37: 3360.54 | L37: 028 000 000 | M37: 2-LIB | N37: 23/07/26 | O37: 30/07/26 | P37: 157,51 | Q37: 703 | R37: willian | S37: 331 | T37: 00510 | U37: MIRANDA | V37: A
A38: =OFFSET(hoje12_326_sp8,37,1,1,1)&"."&OFFSET(hoje12_326_sp8,37,16,1,1) -> 2416.703 | B38: 2416 | C38: BATISTA QUADROS E CIA | D38: 5348350000167 | E38: 12,17 | F38: 51201 | G38: BANCO ITAU | H38: 08 | I38: 369,94- | J38: 0,00 | K38: 1701.86 | L38: 028 000 000 | M38: 2-LIB | N38: 23/07/26 | O38: 30/07/26 | P38: 61,50 | Q38: 703 | R38: willian | S38: 033 | T38: 00168 | U38: AQUIDAUANA | V38: A
A39: =OFFSET(hoje12_326_sp8,38,1,1,1)&"."&OFFSET(hoje12_326_sp8,38,16,1,1) -> 2417.703 | B39: 2417 | C39: BATISTA QUADROS E CIA | D39: 5348350000248 | E39: 15,36 | F39: 51201 | G39: BANCO ITAU | H39: 08 | I39: 288,62- | J39: 0,00 | K39: 1678.18 | L39: 028 000 000 | M39: 2-LIB | N39: 23/07/26 | O39: 30/07/26 | P39: 49,95 | Q39: 703 | R39: willian | S39: 033 | T39: 00162 | U39: AQUIDAUANA | V39: A
A40: =OFFSET(hoje12_326_sp8,39,1,1,1)&"."&OFFSET(hoje12_326_sp8,39,16,1,1) -> 2418.703 | B40: 2418 | C40: BATISTA QUADROS E CIA | D40: 5348350000329 | E40: 15,63 | F40: 51201 | G40: BANCO ITAU | H40: 08 | I40: 407,65- | J40: 0,00 | K40: 2429.87 | L40: 028 000 000 | M40: 2-LIB | N40: 23/07/26 | O40: 30/07/26 | P40: 87,17 | Q40: 703 | R40: willian | S40: 033 | T40: 00276 | U40: ANASTACIO | V40: A
A41: =OFFSET(hoje12_326_sp8,40,1,1,1)&"."&OFFSET(hoje12_326_sp8,40,16,1,1) -> 2419.703 | B41: 2419 | C41: BATISTA QUADROS E CIA | D41: 5348350000400 | E41: 13,63 | F41: 51201 | G41: BANCO ITAU | H41: 08 | I41: 300,04- | J41: 0,00 | K41: 1837.88 | L41: 028 000 000 | M41: 2-LIB | N41: 23/07/26 | O41: 30/07/26 | P41: 72,18 | Q41: 703 | R41: willian | S41: 033 | T41: 00216 | U41: ANASTACIO | V41: A
A42: =OFFSET(hoje12_326_sp8,41,1,1,1)&"."&OFFSET(hoje12_326_sp8,41,16,1,1) -> 2420.703 | B42: 2420 | C42: CACIQUE SUPERMERCADO | D42: 19851425000132 | E42: 15,65 | F42: 51201 | G42: BANCO ITAU | H42: 08 | I42: 216,55- | J42: 0,00 | K42: 1688.63 | L42: 007 000 000 | M42: 2-LIB | N42: 23/07/26 | O42: 30/07/26 | P42: 69,94 | Q42: 703 | R42: kuba | S42: 331 | T42: 00162 | U42: MIRANDA | V42: A
A43: =OFFSET(hoje12_326_sp8,42,1,1,1)&"."&OFFSET(hoje12_326_sp8,42,16,1,1) -> 2424.703 | B43: 2424 | C43: ESSENCIAL ATACADO LTD | D43: 14071909000145 | E43: 22,02 | F43: 51201 | G43: BANCO ITAU | H43: 08 | I43: 1.082,22- | J43: 0,00 | K43: 24976.42 | L43: 021 028 035 | M43: 2-LIB | N43: 30/07/26 | O43: 30/07/26 | P43: 712,14 | Q43: 703 | R43: kuba | S43: 033 | T43: 03486 | U43: ANASTACIO | V43: A
A44: =OFFSET(hoje12_326_sp8,43,1,1,1)&"."&OFFSET(hoje12_326_sp8,43,16,1,1) -> 2431.703 | B44: 2431 | C44: BATISTA QUADROS E CIA | D44: 5348350000167 | E44: 23,05 | F44: 51201 | G44: BANCO ITAU | H44: 08 | I44: 819,92- | J44: 0,00 | K44: 19904.12 | L44: 028 000 000 | M44: 2-LIB | N44: 30/07/26 | O44: 30/07/26 | P44: 615,96 | Q44: 703 | R44: kuba | S44: 033 | T44: 03642 | U44: AQUIDAUANA | V44: A
A45: =OFFSET(hoje12_326_sp8,44,1,1,1)&"."&OFFSET(hoje12_326_sp8,44,16,1,1) -> 2432.703 | B45: 2432 | C45: BATISTA QUADROS E CIA | D45: 5348350000248 | E45: 22,16 | F45: 51201 | G45: BANCO ITAU | H45: 08 | I45: 116,56- | J45: 0,00 | K45: 953.27 | L45: 028 000 000 | M45: 2-LIB | N45: 30/07/26 | O45: 30/07/26 | P45: 31,92 | Q45: 703 | R45: willian | S45: 033 | T45: 00084 | U45: AQUIDAUANA | V45: A
A46: =OFFSET(hoje12_326_sp8,45,1,1,1)&"."&OFFSET(hoje12_326_sp8,45,16,1,1) -> 2433.703 | B46: 2433 | C46: DAMASCENO E DAMASCENO | D46: 1274396000632 | E46: 18,43 | F46: 51201 | G46: BANCO ITAU | H46: 08 | I46: 954,26- | J46: 0,00 | K46: 8382.3 | L46: 028 000 000 | M46: 2-LIB | N46: 30/07/26 | O46: 30/07/26 | P46: 164,72 | Q46: 703 | R46: willian | S46: 330 | T46: 00506 | U46: ANASTACIO | V46: A
A47: =OFFSET(hoje12_326_sp8,46,1,1,1)&"."&OFFSET(hoje12_326_sp8,46,16,1,1) -> 2434.703 | B47: 2434 | C47: DAMASCENO E DAMASCENO | D47: 1274396000209 | E47: 19,59 | F47: 51201 | G47: BANCO ITAU | H47: 08 | I47: 100,77- | J47: 0,00 | K47: 789.63 | L47: 028 000 000 | M47: 2-LIB | N47: 30/07/26 | O47: 30/07/26 | P47: 25,16 | Q47: 703 | R47: willian | S47: 330 | T47: 00072 | U47: ANASTACIO | V47: A
A48: =OFFSET(hoje12_326_sp8,47,1,1,1)&"."&OFFSET(hoje12_326_sp8,47,16,1,1) -> 2435.703 | B48: 2435 | C48: DAMASCENO E DAMASCENO | D48: 1274396000390 | E48: 19,90 | F48: 51201 | G48: BANCO ITAU | H48: 08 | I48: 101,97- | J48: 0,00 | K48: 848.55 | L48: 028 000 000 | M48: 2-LIB | N48: 30/07/26 | O48: 30/07/26 | P48: 28,52 | Q48: 703 | R48: willian | S48: 330 | T48: 00084 | U48: AQUIDAUANA | V48: A
A49: =OFFSET(hoje12_326_sp8,48,1,1,1)&"."&OFFSET(hoje12_326_sp8,48,16,1,1) -> 2436.703 | B49: 2436 | C49: DAMASCENO E DAMASCENO | D49: 1274396000713 | E49: 20,13 | F49: 51201 | G49: BANCO ITAU | H49: 08 | I49: 90,81- | J49: 0,00 | K49: 733.22 | L49: 028 000 000 | M49: 2-LIB | N49: 30/07/26 | O49: 30/07/26 | P49: 24,18 | Q49: 703 | R49: willian | S49: 331 | T49: 00066 | U49: MIRANDA | V49: A
A50: =OFFSET(hoje12_326_sp8,49,1,1,1)&"."&OFFSET(hoje12_326_sp8,49,16,1,1) -> 2437.703 | B50: 2437 | C50: DAMASCENO E DAMASCENO | D50: 1274396000802 | E50: 19,68 | F50: 51201 | G50: BANCO ITAU | H50: 08 | I50: 144,25- | J50: 0,00 | K50: 1088.21 | L50: 028 000 000 | M50: 2-LIB | N50: 30/07/26 | O50: 30/07/26 | P50: 35,85 | Q50: 703 | R50: willian | S50: 039 | T50: 00096 | U50: CHAPADAO DO SUL | V50: A
A51: =OFFSET(hoje12_326_sp8,50,1,1,1)&"."&OFFSET(hoje12_326_sp8,50,16,1,1) -> 2438.703 | B51: 2438 | C51: DAMASCENO E DAMASCENO | D51: 1274396000985 | E51: 19,46 | F51: 51201 | G51: BANCO ITAU | H51: 08 | I51: 151,42- | J51: 0,00 | K51: 1152.74 | L51: 028 000 000 | M51: 2-LIB | N51: 30/07/26 | O51: 30/07/26 | P51: 40,33 | Q51: 703 | R51: willian | S51: 331 | T51: 00102 | U51: MIRANDA | V51: A
A52: =OFFSET(hoje12_326_sp8,51,1,1,1)&"."&OFFSET(hoje12_326_sp8,51,16,1,1) -> 2439.703 | B52: 2439 | C52: DAMASCENO E DAMASCENO | D52: 1274396001019 | E52: 18,38 | F52: 51201 | G52: BANCO ITAU | H52: 08 | I52: 911,87- | J52: 0,00 | K52: 7900.83 | L52: 028 000 000 | M52: 2-LIB | N52: 30/07/26 | O52: 30/07/26 | P52: 152,88 | Q52: 703 | R52: willian | S52: 330 | T52: 00464 | U52: AQUIDAUANA | V52: A
A53: =OFFSET(hoje12_326_sp8,52,1,1,1)&"."&OFFSET(hoje12_326_sp8,52,16,1,1) -> 2440.703 | B53: 2440 | C53: BATISTA QUADROS E CIA | D53: 5348350000329 | E53: 21,83 | F53: 51201 | G53: BANCO ITAU | H53: 08 | I53: 116,56- | J53: 0,00 | K53: 891.95 | L53: 028 000 000 | M53: 2-LIB | N53: 30/07/26 | O53: 30/07/26 | P53: 28,56 | Q53: 703 | R53: willian | S53: 033 | T53: 00072 | U53: ANASTACIO | V53: A
A54: =OFFSET(hoje12_326_sp8,53,1,1,1)&"."&OFFSET(hoje12_326_sp8,53,16,1,1) -> 2441.703 | B54: 2441 | C54: TOMAZI E GOLFETI LTDA | D54: 19222566000196 | E54: 28,31 | F54: 51201 | G54: BANCO ITAU | H54: 08 | I54: 10,49- | J54: 0,00 | K54: 514.5 | L54: 021 035 000 | M54: 1-BLO | N54: 30/07/26 | O54: 30/07/26 | P54: 13,75 | Q54: 703 | R54: kuba | S54: 033 | T54: 00052 | U54: AQUIDAUANA | V54: A
A55: =OFFSET(hoje12_326_sp8,54,1,1,1)&"."&OFFSET(hoje12_326_sp8,54,16,1,1) -> 703001.703 | B55: 703001 | C55: DAMASCENO E DAMASCENO | D55: 1274396000632 | E55: 30,46 | F55: 51201 | G55: BANCO ITAU | H55: 08 | I55: 0,00 | J55: 0,00 | K55: 178.56 | L55: 028 000 000 | M55: 2-LIB | N55: 29/07/26 | O55: 30/07/26 | P55: 2,37 | Q55: 703 | R55: vinicius | S55: 330 | T55: 00012 | U55: ANASTACIO | V55: A
A56: =OFFSET(hoje12_326_sp8,55,1,1,1)&"."&OFFSET(hoje12_326_sp8,55,16,1,1) -> 703002.703 | B56: 703002 | C56: DAMASCENO E DAMASCENO | D56: 1274396000985 | E56: 30,46 | F56: 51201 | G56: BANCO ITAU | H56: 08 | I56: 0,00 | J56: 0,00 | K56: 178.56 | L56: 028 000 000 | M56: 2-LIB | N56: 29/07/26 | O56: 30/07/26 | P56: 2,37 | Q56: 703 | R56: vinicius | S56: 331 | T56: 00012 | U56: MIRANDA | V56: A
A57: =OFFSET(hoje12_326_sp8,56,1,1,1)&"."&OFFSET(hoje12_326_sp8,56,16,1,1) -> 703003.703 | B57: 703003 | C57: DAMASCENO E DAMASCENO | D57: 1274396001019 | E57: 30,46 | F57: 51201 | G57: BANCO ITAU | H57: 08 | I57: 0,00 | J57: 0,00 | K57: 178.56 | L57: 028 000 000 | M57: 2-LIB | N57: 29/07/26 | O57: 30/07/26 | P57: 2,37 | Q57: 703 | R57: vinicius | S57: 330 | T57: 00012 | U57: AQUIDAUANA | V57: A
A58: =OFFSET(hoje12_326_sp8,57,1,1,1)&"."&OFFSET(hoje12_326_sp8,57,16,1,1) -> 703004.703 | B58: 703004 | C58: AQUINO COMERCIO VAREJ | D58: 1547436000168 | E58: 32,34 | F58: 51201 | G58: BANCO ITAU | H58: 08 | I58: 0,00 | J58: 0,00 | K58: 183.54 | L58: 028 000 000 | M58: 2-LIB | N58: 29/07/26 | O58: 30/07/26 | P58: 2,37 | Q58: 703 | R58: vinicius | S58: 331 | T58: 00012 | U58: BODOQUENA | V58: A
A59: =OFFSET(hoje12_326_sp8,58,1,1,1)&"."&OFFSET(hoje12_326_sp8,58,16,1,1) -> 704001.704 | B59: 704001 | C59: SUPERMERCADO JORGE LT | D59: 5027616000170 | E59: 30,46 | F59: 51201 | G59: BANCO ITAU | H59: 08 | I59: 0,00 | J59: 0,00 | K59: 178.56 | L59: 028 000 000 | M59: 2-LIB | N59: 29/07/26 | O59: 30/07/26 | P59: 2,37 | Q59: 704 | R59: vinicius | S59: 044 | T59: 00012 | U59: FATIMA DO SUL | V59: A
A60: =OFFSET(hoje12_326_sp8,59,1,1,1)&"."&OFFSET(hoje12_326_sp8,59,16,1,1) -> 2745.704 | B60: 2745 | C60: JCHAGAS ALIMENTOS LTD | D60: 6813685001496 | E60: 25,65 | F60: 51201 | G60: PIX | H60: 08 | I60: 1.959,19- | J60: 0,00 | K60: 90755.04 | L60: 000 000 000 | M60: ***** | N60: 27/07/26 | O60: 30/07/26 | P60: 2.678,00 | Q60: 704 | R60: willian | S60: 042 | T60: 17404 | U60: NAVIRAI | V60: I
A61: =OFFSET(hoje12_326_sp8,60,1,1,1)&"."&OFFSET(hoje12_326_sp8,60,16,1,1) -> 2746.704 | B61: 2746 | C61: JCHAGAS ALIMENTOS LTD | D61: 6813685001496 | E61: 23,26 | F61: 59901 | G61: BONIFICACA | H61: 08 | I61: 1.628,40- | J61: 0,00 | K61: 1628.4 | L61: 000 000 000 | M61: ***** | N61: 27/07/26 | O61: 30/07/26 | P61: 37,17 | Q61: 704 | R61: willian | S61: 042 | T61: 00354 | U61: NAVIRAI | V61: I
A62: =OFFSET(hoje12_326_sp8,61,1,1,1)&"."&OFFSET(hoje12_326_sp8,61,16,1,1) -> 2747.704 | B62: 2747 | C62: JCHAGAS ALIMENTOS LTD | D62: 6813685001577 | E62: 28,04 | F62: 51201 | G62: PIX | H62: 08 | I62: 1.141,68- | J62: 0,00 | K62: 57683.67 | L62: 000 000 000 | M62: ***** | N62: 27/07/26 | O62: 30/07/26 | P62: 1.681,00 | Q62: 704 | R62: willian | S62: 340 | T62: 10614 | U62: CORUMBA | V62: I
A63: =OFFSET(hoje12_326_sp8,62,1,1,1)&"."&OFFSET(hoje12_326_sp8,62,16,1,1) -> 3249.705 | B63: 3249 | C63: JOSE MANUEL DE JESUS | D63: 15901440000197 | E63: 28,08 | F63: 51201 | G63: BANCO ITAU | H63: 08 | I63: 345,61- | J63: 0,00 | K63: 9244.88 | L63: 014 021 028 | M63: 2-LIB | N63: 30/07/26 | O63: 30/07/26 | P63: 225,00 | Q63: 705 | R63: kuba | S63: 045 | T63: 00808 | U63: BATAYPORA | V63: A
A64: =OFFSET(hoje12_326_sp8,63,1,1,1)&"."&OFFSET(hoje12_326_sp8,63,16,1,1) -> 3270.705 | B64: 3270 | C64: JAIR DOS SANTOS LTDA | D64: 20064302000130 | E64: 20,68 | F64: 51201 | G64: BANCO ITAU | H64: 05 | I64: 3,79- | J64: 0,00 | K64: 552.18 | L64: 021 028 000 | M64: 2-LIB | N64: 27/07/26 | O64: 30/07/26 | P64: 16,93 | Q64: 705 | R64: willian | S64: 441 | T64: 00018 | U64: IVINHEMA | V64: A
A65: =OFFSET(hoje12_326_sp8,64,1,1,1)&"."&OFFSET(hoje12_326_sp8,64,16,1,1) -> 3277.705 | B65: 3277 | C65: COOP AGROINDUSTRIAL V | D65: 15508682000115 | E65: 24,58 | F65: 51201 | G65: BANCO ITAU | H65: 08 | I65: 256,87- | J65: 0,00 | K65: 8148.76 | L65: 021 028 035 | M65: 2-LIB | N65: 29/07/26 | O65: 30/07/26 | P65: 247,84 | Q65: 705 | R65: kuba | S65: 045 | T65: 00680 | U65: NOVA ANDRADINA | V65: A
A66: =OFFSET(hoje12_326_sp8,65,1,1,1)&"."&OFFSET(hoje12_326_sp8,65,16,1,1) -> 705001.705 | B66: 705001 | C66: CRISPINIANO SUPERMERC | D66: 12934721000158 | E66: 30,46 | F66: 51201 | G66: BANCO ITAU | H66: 08 | I66: 0,00 | J66: 0,00 | K66: 178.56 | L66: 035 000 000 | M66: 2-LIB | N66: 29/07/26 | O66: 30/07/26 | P66: 2,37 | Q66: 705 | R66: vinicius | S66: 441 | T66: 00012 | U66: IVINHEMA | V66: A
A67: =OFFSET(hoje12_326_sp8,66,1,1,1)&"."&OFFSET(hoje12_326_sp8,66,16,1,1) -> 2606.708 | B67: 2606 | C67: BENFICA SUPERMERCADOS | D67: 37532249000158 | E67: 6,44 | F67: 51201 | G67: BANCO ITAU | H67: 08 | I67: 321,65- | J67: 0,00 | K67: 1273.03 | L67: 021 000 000 | M67: 2-LIB | N67: 27/07/26 | O67: 30/07/26 | P67: 55,91 | Q67: 708 | R67: willian | S67: 410 | T67: 00144 | U67: SAO GABRIEL DO OESTE | V67: A
A68: =OFFSET(hoje12_326_sp8,67,1,1,1)&"."&OFFSET(hoje12_326_sp8,67,16,1,1) -> 2609.708 | B68: 2609 | C68: MERCADO JOTALI LTDA | D68: 1602811000125 | E68: 7,33 | F68: 51201 | G68: BANCO ITAU | H68: 08 | I68: 156,75- | J68: 0,00 | K68: 613.11 | L68: 021 000 000 | M68: 2-LIB | N68: 29/07/26 | O68: 30/07/26 | P68: 21,03 | Q68: 708 | R68: kuba | S68: 041 | T68: 00075 | U68: COXIM | V68: A
A69: =OFFSET(hoje12_326_sp8,68,1,1,1)&"."&OFFSET(hoje12_326_sp8,68,16,1,1) -> 2625.708 | B69: 2625 | C69: IRMAOS GP COMERCIO E | D69: 3735605000119 | E69: 10,01 | F69: 51201 | G69: BANCO ITAU | H69: 08 | I69: 824,39- | J69: 0,00 | K69: 3269.23 | L69: 021 028 000 | M69: 2-LIB | N69: 30/07/26 | O69: 30/07/26 | P69: 90,91 | Q69: 708 | R69: kuba | S69: 041 | T69: 00318 | U69: COXIM | V69: A
A70: =OFFSET(hoje12_326_sp8,69,1,1,1)&"."&OFFSET(hoje12_326_sp8,69,16,1,1) -> 2626.708 | B70: 2626 | C70: COMERCIAL DE ALIMENTO | D70: 19088260000199 | E70: 7,84 | F70: 51201 | G70: BANCO ITAU | H70: 08 | I70: 889,62- | J70: 0,00 | K70: 3530.91 | L70: 028 000 000 | M70: 2-LIB | N70: 30/07/26 | O70: 30/07/26 | P70: 103,38 | Q70: 708 | R70: kuba | S70: 041 | T70: 00384 | U70: COXIM | V70: A
A71: =OFFSET(hoje12_326_sp8,70,1,1,1)&"."&OFFSET(hoje12_326_sp8,70,16,1,1) -> 2628.708 | B71: 2628 | C71: UNIBEM ATACADISTA LTD | D71: 43437785000177 | E71: 9,36 | F71: 51201 | G71: BANCO ITAU | H71: 08 | I71: 591,32- | J71: 0,00 | K71: 2265.16 | L71: 021 028 000 | M71: 2-LIB | N71: 30/07/26 | O71: 30/07/26 | P71: 91,76 | Q71: 708 | R71: kuba | S71: 041 | T71: 00450 | U71: SONORA | V71: A
A72: =OFFSET(hoje12_326_sp8,71,1,1,1)&"."&OFFSET(hoje12_326_sp8,71,16,1,1) -> 2648.708 | B72: 2648 | C72: D P DA SILVEIRA | D72: 5327650000160 | E72: 35,13 | F72: 51201 | G72: BANCO ITAU | H72: 08 | I72: 2,15- | J72: 0,00 | K72: 104.71 | L72: 021 000 000 | M72: 1-BLO | N72: 30/07/26 | O72: 30/07/26 | P72: 3,41 | Q72: 708 | R72: kuba | S72: 041 | T72: 00018 | U72: RIO VERDE DE MATO GROSSO | V72: A
A73: =OFFSET(hoje12_326_sp8,72,1,1,1)&"."&OFFSET(hoje12_326_sp8,72,16,1,1) -> 2649.708 | B73: 2649 | C73: ATACADO DA CASA LTDA | D73: 5318045000122 | E73: 26,68 | F73: 51201 | G73: BANCO ITAU | H73: 08 | I73: 5,73- | J73: 0,00 | K73: 280.23 | L73: 021 000 000 | M73: 1-BLO | N73: 30/07/26 | O73: 30/07/26 | P73: 26,91 | Q73: 708 | R73: kuba | S73: 041 | T73: 00030 | U73: RIO VERDE DE MATO GROSSO | V73: A
A74: =OFFSET(hoje12_326_sp8,73,1,1,1)&"."&OFFSET(hoje12_326_sp8,73,16,1,1) -> 2650.708 | B74: 2650 | C74: NELSON ARGENTINO JUNI | D74: 49540108000166 | E74: 25,97 | F74: 51201 | G74: PIX | H74: 09 | I74: 2,89- | J74: 0,00 | K74: 141.79 | L74: 000 000 000 | M74: ***** | N74: 30/07/26 | O74: 30/07/26 | P74: 3,48 | Q74: 708 | R74: kuba | S74: 041 | T74: 00014 | U74: ALCINOPOLIS | V74: A
A75: =OFFSET(hoje12_326_sp8,74,1,1,1)&"."&OFFSET(hoje12_326_sp8,74,16,1,1) -> 2651.708 | B75: 2651 | C75: IM DO NASCIMENTO | D75: 8650875000140 | E75: 34,38 | F75: 51201 | G75: PIX | H75: 09 | I75: 1,38- | J75: 0,00 | K75: 100.02 | L75: 000 000 000 | M75: ***** | N75: 30/07/26 | O75: 30/07/26 | P75: 4,01 | Q75: 708 | R75: kuba | S75: 041 | T75: 00015 | U75: SONORA | V75: A
A76: =OFFSET(hoje12_326_sp8,75,1,1,1)&"."&OFFSET(hoje12_326_sp8,75,16,1,1) -> 2652.708 | B76: 2652 | C76: JOSE CARDOSO DOS SANT | D76: 40242188000107 | E76: 28,36 | F76: 51201 | G76: BANCO ITAU | H76: 09 | I76: 2,10- | J76: 0,00 | K76: 102.65 | L76: 021 000 000 | M76: ***** | N76: 30/07/26 | O76: 30/07/26 | P76: 3,80 | Q76: 708 | R76: kuba | S76: 041 | T76: 00021 | U76: SONORA | V76: A
A77: =OFFSET(hoje12_326_sp8,76,1,1,1)&"."&OFFSET(hoje12_326_sp8,76,16,1,1) -> 2653.708 | B77: 2653 | C77: IVANETE CARVALHO SOUZ | D77: 26827733000198 | E77: 26,72 | F77: 51201 | G77: BANCO ITAU | H77: 09 | I77: 6,54- | J77: 0,00 | K77: 320.85 | L77: 021 000 000 | M77: 1-BLO | N77: 30/07/26 | O77: 30/07/26 | P77: 27,55 | Q77: 708 | R77: kuba | S77: 041 | T77: 00036 | U77: PEDRO GOMES | V77: A
A78: =OFFSET(hoje12_326_sp8,77,1,1,1)&"."&OFFSET(hoje12_326_sp8,77,16,1,1) -> 2654.708 | B78: 2654 | C78: GESSI DOS SANTOS SALO | D78: 7317095000110 | E78: 27,20 | F78: 51201 | G78: BANCO ITAU | H78: 09 | I78: 5,24- | J78: 0,00 | K78: 256.39 | L78: 028 000 000 | M78: 1-BLO | N78: 30/07/26 | O78: 30/07/26 | P78: 21,25 | Q78: 708 | R78: kuba | S78: 041 | T78: 00033 | U78: PEDRO GOMES | V78: A
A79: =OFFSET(hoje12_326_sp8,78,1,1,1)&"."&OFFSET(hoje12_326_sp8,78,16,1,1) -> 2655.708 | B79: 2655 | C79: JOSE HIVANO GUILHERME | D79: 24196029000159 | E79: 34,07 | F79: 51201 | G79: PIX | H79: 05 | I79: 1,16- | J79: 0,00 | K79: 100.3 | L79: 000 000 000 | M79: ***** | N79: 30/07/26 | O79: 30/07/26 | P79: 3,96 | Q79: 708 | R79: kuba | S79: 041 | T79: 00018 | U79: COXIM | V79: A
A80: =OFFSET(hoje12_326_sp8,79,1,1,1)&"."&OFFSET(hoje12_326_sp8,79,16,1,1) -> 2657.708 | B80: 2657 | C80: TIAGO SANTOS FREITAS | D80: 19621681000133 | E80: 27,13 | F80: 51201 | G80: BANCO ITAU | H80: 08 | I80: 2,58- | J80: 0,00 | K80: 126.5 | L80: 021 000 000 | M80: ***** | N80: 30/07/26 | O80: 30/07/26 | P80: 2,47 | Q80: 708 | R80: kuba | S80: 041 | T80: 00005 | U80: RIO VERDE DE MATO GROSSO | V80: A
A81: =OFFSET(hoje12_326_sp8,80,1,1,1)&"."&OFFSET(hoje12_326_sp8,80,16,1,1) -> 2659.708 | B81: 2659 | C81: IRMAOS GP COMERCIO E | D81: 3735605000119 | E81: 36,44 | F81: 51201 | G81: BANCO ITAU | H81: 08 | I81: 2,20- | J81: 0,00 | K81: 108.1 | L81: 021 000 000 | M81: 2-LIB | N81: 30/07/26 | O81: 30/07/26 | P81: 2,90 | Q81: 708 | R81: kuba | S81: 041 | T81: 00010 | U81: COXIM | V81: A
A82: =OFFSET(hoje12_326_sp8,81,1,1,1)&"."&OFFSET(hoje12_326_sp8,81,16,1,1) -> 2660.708 | B82: 2660 | C82: COMERCIAL DE ALIMENTO | D82: 19088260000199 | E82: 35,51 | F82: 51201 | G82: BANCO ITAU | H82: 08 | I82: 2,16- | J82: 0,00 | K82: 106.54 | L82: 021 000 000 | M82: 1-BLO | N82: 30/07/26 | O82: 30/07/26 | P82: 2,90 | Q82: 708 | R82: kuba | S82: 041 | T82: 00010 | U82: COXIM | V82: A
A83: =OFFSET(hoje12_326_sp8,82,1,1,1)&"."&OFFSET(hoje12_326_sp8,82,16,1,1) -> 2661.708 | B83: 2661 | C83: V LUNARDELLO DA SILVA | D83: 59844699000119 | E83: 6,17 | F83: 51201 | G83: PIX | H83: 09 | I83: 233,63- | J83: 0,00 | K83: 907.18 | L83: 000 000 000 | M83: ***** | N83: 30/07/26 | O83: 30/07/26 | P83: 24,21 | Q83: 708 | R83: kuba | S83: 041 | T83: 00108 | U83: COXIM | V83: A
A84: =OFFSET(hoje12_326_sp8,83,1,1,1)&"."&OFFSET(hoje12_326_sp8,83,16,1,1) -> 708001.708 | B84: 708001 | C84: IRMAOS GP COMERCIO E | D84: 3735605000119 | E84: 32,34 | F84: 51201 | G84: BANCO ITAU | H84: 08 | I84: 0,00 | J84: 0,00 | K84: 183.54 | L84: 028 000 000 | M84: 2-LIB | N84: 29/07/26 | O84: 30/07/26 | P84: 2,37 | Q84: 708 | R84: vinicius | S84: 041 | T84: 00012 | U84: COXIM | V84: A
A85: =OFFSET(hoje12_326_sp8,84,1,1,1)&"."&OFFSET(hoje12_326_sp8,84,16,1,1) -> 708002.708 | B85: 708002 | C85: COMERCIAL DE ALIMENTO | D85: 19088260000199 | E85: 30,46 | F85: 51201 | G85: BANCO ITAU | H85: 08 | I85: 0,00 | J85: 0,00 | K85: 178.56 | L85: 028 000 000 | M85: 2-LIB | N85: 29/07/26 | O85: 30/07/26 | P85: 2,37 | Q85: 708 | R85: vinicius | S85: 041 | T85: 00012 | U85: COXIM | V85: A
A86: =OFFSET(hoje12_326_sp8,85,1,1,1)&"."&OFFSET(hoje12_326_sp8,85,16,1,1) -> 708003.708 | B86: 708003 | C86: UNIBEM ATACADISTA LTD | D86: 43437785000177 | E86: 30,46 | F86: 51201 | G86: BANCO ITAU | H86: 08 | I86: 0,00 | J86: 0,00 | K86: 178.56 | L86: 028 000 000 | M86: 2-LIB | N86: 29/07/26 | O86: 30/07/26 | P86: 2,37 | Q86: 708 | R86: vinicius | S86: 041 | T86: 00012 | U86: SONORA | V86: A
A87: =OFFSET(hoje12_326_sp8,86,1,1,1)&"."&OFFSET(hoje12_326_sp8,86,16,1,1) -> 1482.710 | B87: 1482 | C87: SUPERMERCADO JORGE LT | D87: 5027616000170 | E87: 25,25 | F87: 51201 | G87: BANCO ITAU | H87: 08 | I87: 836,28- | J87: 0,00 | K87: 27064.61 | L87: 028 000 000 | M87: 2-LIB | N87: 30/07/26 | O87: 30/07/26 | P87: 500,57 | Q87: 710 | R87: kuba | S87: 044 | T87: 03026 | U87: FATIMA DO SUL | V87: A
A88: =OFFSET(hoje12_326_sp8,87,1,1,1)&"."&OFFSET(hoje12_326_sp8,87,16,1,1) -> 1486.710 | B88: 1486 | C88: COMERCIAL JULIFRAN LT | D88: 37570181000100 | E88: 20,14 | F88: 51201 | G88: BANCO ITAU | H88: 08 | I88: 1.984,72- | J88: 0,00 | K88: 27120.86 | L88: 007 012 017 | M88: 1-BLO | N88: 30/07/26 | O88: 30/07/26 | P88: 758,96 | Q88: 710 | R88: kuba | S88: 044 | T88: 04140 | U88: FATIMA DO SUL | V88: A
A89: =OFFSET(hoje12_326_sp8,88,1,1,1)&"."&OFFSET(hoje12_326_sp8,88,16,1,1) -> 1487.710 | B89: 1487 | C89: COMERCIAL JULIFRAN LT | D89: 37570181000100 | E89: 22,07 | F89: 59901 | G89: BONIFICACA | H89: 08 | I89: 717,90- | J89: 0,00 | K89: 702.01 | L89: 000 000 000 | M89: 1-BLO | N89: 30/07/26 | O89: 30/07/26 | P89: 24,09 | Q89: 710 | R89: kuba | S89: 044 | T89: 00147 | U89: FATIMA DO SUL | V89: A
A90: =OFFSET(hoje12_326_sp8,89,1,1,1)&"."&OFFSET(hoje12_326_sp8,89,16,1,1) -> 1488.710 | B90: 1488 | C90: ABIR CRISPINIANO LTDA | D90: 551975000531 | E90: 23,97 | F90: 51201 | G90: BANCO ITAU | H90: 08 | I90: 248,41- | J90: 0,00 | K90: 8140.26 | L90: 035 000 000 | M90: 1-BLO | N90: 30/07/26 | O90: 30/07/26 | P90: 99,67 | Q90: 710 | R90: kuba | S90: 044 | T90: 00687 | U90: DEODAPOLIS | V90: A
A91: =OFFSET(hoje12_326_sp8,90,1,1,1)&"."&OFFSET(hoje12_326_sp8,90,16,1,1) -> 2459.711 | B91: 2459 | C91: SUPERMERCADO THOME - | D91: 33768854000171 | E91: 29,11 | F91: 51201 | G91: BANCO ITAU | H91: 08 | I91: 31,88- | J91: 0,00 | K91: 700.72 | L91: 021 000 000 | M91: 2-LIB | N91: 23/07/26 | O91: 30/07/26 | P91: 9,48 | Q91: 711 | R91: kuba | S91: 307 | T91: 00048 | U91: TRES LAGOAS | V91: A
A92: =OFFSET(hoje12_326_sp8,91,1,1,1)&"."&OFFSET(hoje12_326_sp8,91,16,1,1) -> 711001.711 | B92: 711001 | C92: SUPERMERCADO THOME - | D92: 33768854000171 | E92: 30,46 | F92: 51201 | G92: BANCO ITAU | H92: 08 | I92: 0,00 | J92: 0,00 | K92: 178.56 | L92: 035 000 000 | M92: 2-LIB | N92: 29/07/26 | O92: 30/07/26 | P92: 2,37 | Q92: 711 | R92: vinicius | S92: 307 | T92: 00012 | U92: TRES LAGOAS | V92: A
A93: =OFFSET(hoje12_326_sp8,92,1,1,1)&"."&OFFSET(hoje12_326_sp8,92,16,1,1) -> 2478.711 | B93: 2478 | C93: SETE PHARMA 4 LTDA | D93: 53091979000117 | E93: 32,05 | F93: 51201 | G93: BANCO ITAU | H93: 05 | I93: 5,05- | J93: 0,00 | K93: 201.56 | L93: 021 000 000 | M93: ***** | N93: 30/07/26 | O93: 30/07/26 | P93: 2,23 | Q93: 711 | R93: kuba | S93: 030 | T93: 00009 | U93: TRES LAGOAS | V93: I
A94: =OFFSET(hoje12_326_sp8,93,1,1,1)&"."&OFFSET(hoje12_326_sp8,93,16,1,1) -> 712001.712 | B94: 712001 | C94: GMAIS COMERCIO DE ALI | D94: 33168717000449 | E94: 30,46 | F94: 51201 | G94: BANCO ITAU | H94: 08 | I94: 0,00 | J94: 0,00 | K94: 178.56 | L94: 028 000 000 | M94: 2-LIB | N94: 29/07/26 | O94: 30/07/26 | P94: 2,37 | Q94: 712 | R94: vinicius | S94: 047 | T94: 00012 | U94: JARDIM | V94: A
A95: =OFFSET(hoje12_326_sp8,94,1,1,1)&"."&OFFSET(hoje12_326_sp8,94,16,1,1) -> 712002.712 | B95: 712002 | C95: GMAIS COMERCIO DE ALI | D95: 33168717000104 | E95: 30,46 | F95: 51201 | G95: BANCO ITAU | H95: 08 | I95: 0,00 | J95: 0,00 | K95: 178.56 | L95: 035 000 000 | M95: 2-LIB | N95: 29/07/26 | O95: 30/07/26 | P95: 2,37 | Q95: 712 | R95: vinicius | S95: 047 | T95: 00012 | U95: BONITO | V95: A
A96: =OFFSET(hoje12_326_sp8,95,1,1,1)&"."&OFFSET(hoje12_326_sp8,95,16,1,1) -> 494.715 | B96: 494 | C96: HIPERMERCADO BOM GOST | D96: 15489834000180 | E96: 25,15 | F96: 51201 | G96: BANCO ITAU | H96: 08 | I96: 877,80- | J96: 0,00 | K96: 19952.78 | L96: 028 000 000 | M96: 1-BLO | N96: 30/07/26 | O96: 30/07/26 | P96: 433,38 | Q96: 715 | R96: kuba | S96: 032 | T96: 02094 | U96: PONTA PORA | V96: A
A97: =OFFSET(hoje12_326_sp8,96,1,1,1)&"."&OFFSET(hoje12_326_sp8,96,16,1,1) -> 721001.721 | B97: 721001 | C97: VRA COMERCIO LTDA | D97: 2318826001281 | E97: 30,46 | F97: 51201 | G97: BANCO ITAU | H97: 08 | I97: 0,00 | J97: 0,00 | K97: 178.56 | L97: 028 000 000 | M97: 2-LIB | N97: 29/07/26 | O97: 30/07/26 | P97: 2,37 | Q97: 721 | R97: vinicius | S97: 039 | T97: 00012 | U97: CHAPADAO DO SUL | V97: A
A98: =OFFSET(hoje12_326_sp8,97,1,1,1)&"."&OFFSET(hoje12_326_sp8,97,16,1,1) -> 721002.721 | B98: 721002 | C98: VRA COMERCIO LTDA | D98: 2318826001010 | E98: 30,46 | F98: 51201 | G98: BANCO ITAU | H98: 08 | I98: 0,00 | J98: 0,00 | K98: 178.56 | L98: 028 000 000 | M98: 2-LIB | N98: 29/07/26 | O98: 30/07/26 | P98: 2,37 | Q98: 721 | R98: vinicius | S98: 031 | T98: 00012 | U98: AMAMBAI | V98: A
A99: =OFFSET(hoje12_326_sp8,98,1,1,1)&"."&OFFSET(hoje12_326_sp8,98,16,1,1) -> 721003.721 | B99: 721003 | C99: VRA COMERCIO LTDA | D99: 2318826000390 | E99: 30,46 | F99: 51201 | G99: BANCO ITAU | H99: 08 | I99: 0,00 | J99: 0,00 | K99: 178.56 | L99: 028 000 000 | M99: 2-LIB | N99: 29/07/26 | O99: 30/07/26 | P99: 2,37 | Q99: 721 | R99: vinicius | S99: 441 | T99: 00012 | U99: IVINHEMA | V99: A
A100: =OFFSET(hoje12_326_sp8,99,1,1,1)&"."&OFFSET(hoje12_326_sp8,99,16,1,1) -> 721004.721 | B100: 721004 | C100: VRA COMERCIO LTDA | D100: 2318826000633 | E100: 30,46 | F100: 51201 | G100: BANCO ITAU | H100: 08 | I100: 0,00 | J100: 0,00 | K100: 178.56 | L100: 028 000 000 | M100: 2-LIB | N100: 29/07/26 | O100: 30/07/26 | P100: 2,37 | Q100: 721 | R100: vinicius | S100: 339 | T100: 00012 | U100: COSTA RICA | V100: A
...

Sheet 319
A1: RANK | B1: CNPJ | C1: RAZÃO SOCIAL | D1: CIDADE | E1: ENDEREÇO | F1: PESO BRUTO | G1: CAIXA | H1: VALOR | I1: %PB | J1: %CX | K1: %VLR | L1: %ACP | M1: %ACG | N1: REP | O1: PR MED | P1: CENSO | Q1: =SUM(H:H) -> 4600515 | R1: =COUNT(A:A) -> 761 | S1: =SUBTOTAL(9,H:H) -> 4600515
A2: 1 | B2: 4757459000519 | C2: CD-00 ABV COMERCIO DE AL | D2: DOURADOS | E2: SALETE TEREZINHA HAR | F2: 32505 | G2: 5516 | H2: 1097650.1 | I2: 23.4 | J2: 23.32 | K2: 23.85 | L2: 23.85 | M2: 23.85 | N2: 507 | O2: 0 | P2: A36
A3: 2 | B3: 2318826000200 | C3: VRA COMERCIO LTDA | D3: CORUMBA | E3: PEDRO DE MEDEIROS | F3: 6811 | G3: 874 | H3: 221339.41 | I3: 4.9 | J3: 3.69 | K3: 4.81 | L3: 28.67 | M3: 28.67 | N3: 721 | O3: 0 | P3: A03
A4: 3 | B4: 4822179000113 | C4: CENTRAL ECONOMICA DE DIS | D4: CAMPO GRANDE | E4: AV DOUTOR GUNTER HAN | F4: 6245 | G4: 900 | H4: 175918.17 | I4: 4.49 | J4: 3.8 | K4: 3.82 | L4: 32.49 | M4: 32.49 | N4: 301 | O4: 0 | P4: A15
A5: 4 | B5: 20335148000194 | C5: A R S SUPERMERCADOS LTDA | D5: PONTA PORA | E5: BRASIL | F5: 2980 | G5: 651 | H5: 113356.7 | I5: 2.14 | J5: 2.75 | K5: 2.46 | L5: 34.95 | M5: 34.95 | N5: 507 | O5: 0 | P5: A35
A6: 5 | B6: 20335148000275 | C6: A R S SUPERMERCADOS LTDA | D6: PONTA PORA | E6: AV URUMBELA | F6: 5456 | G6: 575 | H6: 105295.06 | I6: 3.92 | J6: 2.43 | K6: 2.28 | L6: 37.24 | M6: 37.24 | N6: 507 | O6: 0 | P6: A35
A7: 6 | B7: 12887219000133 | C7: NOVA ESTRELA COM DE ALIM | D7: TRES LAGOAS | E7: CLODOALDO GARCIA | F7: 4425 | G7: 1278 | H7: 100366.21 | I7: 3.18 | J7: 5.4 | K7: 2.18 | L7: 39.42 | M7: 39.42 | N7: 211 | O7: 0 | P7: A35
A8: 7 | B8: 9401283000158 | C8: IYOBE E CIA LTDA | D8: PONTA PORA | E8: JORGE ROBERTO SALOMA | F8: 2681 | G8: 273 | H8: 91720.46 | I8: 1.93 | J8: 1.15 | K8: 1.99 | L8: 41.42 | M8: 41.42 | N8: 715 | O8: 0 | P8: A41
A9: 8 | B9: 2318826000633 | C9: VRA COMERCIO LTDA | D9: COSTA RICA | E9: JOSE FERREIRA DA CO | F9: 1925 | G9: 395 | H9: 84468.68 | I9: 1.38 | J9: 1.66 | K9: 1.83 | L9: 43.25 | M9: 43.25 | N9: 721 | O9: 0 | P9: A03
A10: 9 | B10: 6813685001496 | C10: JCHAGAS ALIMENTOS LTDA | D10: NAVIRAI | E10: AV CAMPO GRANDE | F10: 2231 | G10: 374 | H10: 78869.4 | I10: 1.6 | J10: 1.58 | K10: 1.71 | L10: 44.97 | M10: 44.97 | N10: 704 | O10: 0 | P10: A35
A11: 10 | B11: 12887219000214 | C11: NOVA ESTRELA COM DE ALIM | D11: TRES LAGOAS | E11: CAPITAO OLINTO MANCI | F11: 2297 | G11: 536 | H11: 66607.84 | I11: 1.65 | J11: 2.26 | K11: 1.44 | L11: 46.42 | M11: 46.42 | N11: 211 | O11: 0 | P11: A35
A12: 11 | B12: 2318826001281 | C12: VRA COMERCIO LTDA | D12: CHAPADAO DO SUL | E12: AVENIDA ALEMANHA | F12: 1621 | G12: 338 | H12: 66399.07 | I12: 1.16 | J12: 1.42 | K12: 1.44 | L12: 47.86 | M12: 47.86 | N12: 721 | O12: 0 | P12: A35
A13: 12 | B13: 2318826000390 | C13: VRA COMERCIO LTDA | D13: IVINHEMA | E13: BRASIL | F13: 1820 | G13: 358 | H13: 64515.33 | I13: 1.31 | J13: 1.51 | K13: 1.4 | L13: 49.26 | M13: 49.26 | N13: 721 | O13: 0 | P13: A03
... A762: 761 | B762: 6968830000274 | C762: MERCADO BRASIL LTDA | D762: INOCENCIA | E762: ALEXANDRE BATISTA GA | F762: -872 | G762: -115 | H762: -26324.66 | I762: -0.62 | J762: -0.48 | K762: -0.57 | L762: 100 | M762: 100 | N762: 706 | O762: 0 | P762: A15

Sheet 12.326ana
A1: Cod Prod | B1: Desc Prod | C1: Total Vlr | D1: Desc $ | E1: Qtde | F1: Vlr Und | G1: %D.Maxi | H1: %D.Pedido | I1: %DM | J1: Dif $ | K1: Nº Pedido | L1: Rep | M1: CNPJ
A2: 11100009 | B2: AJAX FDF MAR DE FLORES..........01X500ML | C2: 14.73 | D2: 0 | E2: 3 | F2: 4.91 | G2: 0,00 | H2: 0,00 | I2: 0,00 | J2: 0,00 | K2: 1067 | L2: 135 | M2: =IFERROR(VLOOKUP((OFFSET(hoje12_326_ana9,1,10,1,1)&"."&OFFSET(hoje12_326_ana9,1,11,1,1)),'12.326'!A:D,4,0),"-") -> 7691695000144
A3: 11100017 | B3: AJAX FRESH LIMAO................01X500ML | C3: 22.26 | D3: 0 | E3: 3 | F3: 7.42 | G3: 0,00 | H3: 0,00 | I3: 0,00 | J3: 0,00 | K3: 1067 | L3: 135 | M3: =IFERROR(VLOOKUP((OFFSET(hoje12_326_ana9,2,10,1,1)&"."&OFFSET(hoje12_326_ana9,2,11,1,1)),'12.326'!A:D,4,0),"-") -> 7691695000144
A4: 11100034 | B4: AJAX LIMP PERF BOUQUET FLORES...01X500ML | C4: 14.73 | D4: 0 | E4: 3 | F4: 4.91 | G4: 0,00 | H4: 0,00 | I4: 0,00 | J4: 0,00 | K4: 1067 | L4: 135 | M4: =IFERROR(VLOOKUP((OFFSET(hoje12_326_ana9,3,10,1,1)&"."&OFFSET(hoje12_326_ana9,3,11,1,1)),'12.326'!A:D,4,0),"-") -> 7691695000144
A5: 11100059 | B5: CD COLG L12 TRI 90G GT3 LUM 60G.01X 15UN | C5: 117.7 | D5: 0 | E5: 2 | F5: 58.85 | G5: 0,00 | H5: 0,00 | I5: 0,00 | J5: 0,00 | K5: 1067 | L5: 135 | M5: =IFERROR(VLOOKUP((OFFSET(hoje12_326_ana9,4,10,1,1)&"."&OFFSET(hoje12_326_ana9,4,11,1,1)),'12.326'!A:D,4,0),"-") -> 7691695000144
A6: 11100213 | B6: CD SORR DENTES BRANCOS..........01X 50GR | C6: 31.44 | D6: 0 | E6: 12 | F6: 2.62 | G6: 0,00 | H6: 0,00 | I6: 0,00 | J6: 0,00 | K6: 1067 | L6: 135 | M6: =IFERROR(VLOOKUP((OFFSET(hoje12_326_ana9,5,10,1,1)&"."&OFFSET(hoje12_326_ana9,5,11,1,1)),'12.326'!A:D,4,0),"-") -> 7691695000144
A7: 11100689 | B7: SAB PALM MELANCIA E LICHIA......01X 85GR | C7: 49.03 | D7: 2.57 | E7: 24 | F7: 2.15 | G7: 0,00 | H7: 5,00 | I7: 0,00 | J7: 2,58- | K7: 1067 | L7: 135 | M7: =IFERROR(VLOOKUP((OFFSET(hoje12_326_ana9,6,10,1,1)&"."&OFFSET(hoje12_326_ana9,6,11,1,1)),'12.326'!A:D,4,0),"-") -> 7691695000144
A8: 11100728 | B8: SAB PALM TOQ NUT FRAMB E AMORA..01X 85GR | C8: 49.03 | D8: 2.57 | E8: 24 | F8: 2.15 | G8: 0,00 | H8: 5,00 | I8: 0,00 | J8: 2,58- | K8: 1067 | L8: 135 | M8: =IFERROR(VLOOKUP((OFFSET(hoje12_326_ana9,7,10,1,1)&"."&OFFSET(hoje12_326_ana9,7,11,1,1)),'12.326'!A:D,4,0),"-") -> 7691695000144
A9: 11101000 | B9: ED COLG AD SMILES HARRY POTTER..01X 02UN | C9: 68.97 | D9: 0 | E9: 3 | F9: 22.99 | G9: 0,00 | H9: 0,00 | I9: 0,00 | J9: 0,00 | K9: 211001 | L9: 211 | M9: =IFERROR(VLOOKUP((OFFSET(hoje12_326_ana9,8,10,1,1)&"."&OFFSET(hoje12_326_ana9,8,11,1,1)),'12.326'!A:D,4,0),"-") -> 12887219000303
A10: 11100998 | B10: CD COLG LUM WHIT COLOR CORRECT..01X133GR | C10: 45.03 | D10: 0 | E10: 3 | F10: 15.01 | G10: 0,00 | H10: 0,00 | I10: 0,00 | J10: 0,00 | K10: 211001 | L10: 211 | M10: =IFERROR(VLOOKUP((OFFSET(hoje12_326_ana9,9,10,1,1)&"."&OFFSET(hoje12_326_ana9,9,11,1,1)),'12.326'!A:D,4,0),"-") -> 12887219000303
A11: 11101004 | B11: SAB LIQ CORP AMEND ABACAT LEITE.01X250ML | C11: 32.28 | D11: 0 | E11: 3 | F11: 10.76 | G11: 0,00 | H11: 0,00 | I11: 0,00 | J11: 0,00 | K11: 211001 | L11: 211 | M11: =IFERROR(VLOOKUP((OFFSET(hoje12_326_ana9,10,10,1,1)&"."&OFFSET(hoje12_326_ana9,10,11,1,1)),'12.326'!A:D,4,0),"-") -> 12887219000303
A12: 11101003 | B12: SAB LIQ CORP AMORA BANAN IOGURT.01X250ML | C12: 32.28 | D12: 0 | E12: 3 | F12: 10.76 | G12: 0,00 | H12: 0,00 | I12: 0,00 | J12: 0,00 | K12: 211001 | L12: 211 | M12: =IFERROR(VLOOKUP((OFFSET(hoje12_326_ana9,11,10,1,1)&"."&OFFSET(hoje12_326_ana9,11,11,1,1)),'12.326'!A:D,4,0),"-") -> 12887219000303
A13: 11101000 | B13: ED COLG AD SMILES HARRY POTTER..01X 02UN | C13: 68.97 | D13: 0 | E13: 3 | F13: 22.99 | G13: 0,00 | H13: 0,00 | I13: 0,00 | J13: 0,00 | K13: 211002 | L13: 211 | M13: =IFERROR(VLOOKUP((OFFSET(hoje12_326_ana9,12,10,1,1)&"."&OFFSET(hoje12_326_ana9,12,11,1,1)),'12.326'!A:D,4,0),"-") -> 12887219000567
A14: 11100998 | B14: CD COLG LUM WHIT COLOR CORRECT..01X133GR | C14: 45.03 | D14: 0 | E14: 3 | F14: 15.01 | G14: 0,00 | H14: 0,00 | I14: 0,00 | J14: 0,00 | K14: 211002 | L14: 211 | M14: =IFERROR(VLOOKUP((OFFSET(hoje12_326_ana9,13,10,1,1)&"."&OFFSET(hoje12_326_ana9,13,11,1,1)),'12.326'!A:D,4,0),"-") -> 12887219000567
A15: 11101004 | B15: SAB LIQ CORP AMEND ABACAT LEITE.01X250ML | C15: 32.28 | D15: 0 | E15: 3 | F15: 10.76 | G15: 0,00 | H15: 0,00 | I15: 0,00 | J15: 0,00 | K15: 211002 | L15: 211 | M15: =IFERROR(VLOOKUP((OFFSET(hoje12_326_ana9,14,10,1,1)&"."&OFFSET(hoje12_326_ana9,14,11,1,1)),'12.326'!A:D,4,0),"-") -> 12887219000567
A16: 11101003 | B16: SAB LIQ CORP AMORA BANAN IOGURT.01X250ML | C16: 32.28 | D16: 0 | E16: 3 | F16: 10.76 | G16: 0,00 | H16: 0,00 | I16: 0,00 | J16: 0,00 | K16: 211002 | L16: 211 | M16: =IFERROR(VLOOKUP((OFFSET(hoje12_326_ana9,15,10,1,1)&"."&OFFSET(hoje12_326_ana9,15,11,1,1)),'12.326'!A:D,4,0),"-") -> 12887219000567
A17: 11101000 | B17: ED COLG AD SMILES HARRY POTTER..01X 02UN | C17: 68.97 | D17: 0 | E17: 3 | F17: 22.99 | G17: 0,00 | H17: 0,00 | I17: 0,00 | J17: 0,00 | K17: 211003 | L17: 211 | M17: =IFERROR(VLOOKUP((OFFSET(hoje12_326_ana9,16,10,1,1)&"."&OFFSET(hoje12_326_ana9,16,11,1,1)),'12.326'!A:D,4,0),"-") -> 12887219000214
A18: 11100998 | B18: CD COLG LUM WHIT COLOR CORRECT..01X133GR | C18: 45.03 | D18: 0 | E18: 3 | F18: 15.01 | G18: 0,00 | H18: 0,00 | I18: 0,00 | J18: 0,00 | K18: 211003 | L18: 211 | M18: =IFERROR(VLOOKUP((OFFSET(hoje12_326_ana9,17,10,1,1)&"."&OFFSET(hoje12_326_ana9,17,11,1,1)),'12.326'!A:D,4,0),"-") -> 12887219000214
A19: 11101004 | B19: SAB LIQ CORP AMEND ABACAT LEITE.01X250ML | C19: 32.28 | D19: 0 | E19: 3 | F19: 10.76 | G19: 0,00 | H19: 0,00 | I19: 0,00 | J19: 0,00 | K19: 211003 | L19: 211 | M19: =IFERROR(VLOOKUP((OFFSET(hoje12_326_ana9,18,10,1,1)&"."&OFFSET(hoje12_326_ana9,18,11,1,1)),'12.326'!A:D,4,0),"-") -> 12887219000214
A20: 11101003 | B20: SAB LIQ CORP AMORA BANAN IOGURT.01X250ML | C20: 32.28 | D20: 0 | E20: 3 | F20: 10.76 | G20: 0,00 | H20: 0,00 | I20: 0,00 | J20: 0,00 | K20: 211003 | L20: 211 | M20: =IFERROR(VLOOKUP((OFFSET(hoje12_326_ana9,19,10,1,1)&"."&OFFSET(hoje12_326_ana9,19,11,1,1)),'12.326'!A:D,4,0),"-") -> 12887219000214
A21: 11101000 | B21: ED COLG AD SMILES HARRY POTTER..01X 02UN | C21: 68.97 | D21: 0 | E21: 3 | F21: 22.99 | G21: 0,00 | H21: 0,00 | I21: 0,00 | J21: 0,00 | K21: 211004 | L21: 211 | M21: =IFERROR(VLOOKUP((OFFSET(hoje12_326_ana9,20,10,1,1)&"."&OFFSET(hoje12_326_ana9,20,11,1,1)),'12.326'!A:D,4,0),"-") -> 12887219000133
A22: 11100998 | B22: CD COLG LUM WHIT COLOR CORRECT..01X133GR | C22: 45.03 | D22: 0 | E22: 3 | F22: 15.01 | G22: 0,00 | H22: 0,00 | I22: 0,00 | J22: 0,00 | K22: 211004 | L22: 211 | M22: =IFERROR(VLOOKUP((OFFSET(hoje12_326_ana9,21,10,1,1)&"."&OFFSET(hoje12_326_ana9,21,11,1,1)),'12.326'!A:D,4,0),"-") -> 12887219000133
A23: 11101004 | B23: SAB LIQ CORP AMEND ABACAT LEITE.01X250ML | C23: 32.28 | D23: 0 | E23: 3 | F23: 10.76 | G23: 0,00 | H23: 0,00 | I23: 0,00 | J23: 0,00 | K23: 211004 | L23: 211 | M23: =IFERROR(VLOOKUP((OFFSET(hoje12_326_ana9,22,10,1,1)&"."&OFFSET(hoje12_326_ana9,22,11,1,1)),'12.326'!A:D,4,0),"-") -> 12887219000133
A24: 11101003 | B24: SAB LIQ CORP AMORA BANAN IOGURT.01X250ML | C24: 32.28 | D24: 0 | E24: 3 | F24: 10.76 | G24: 0,00 | H24: 0,00 | I24: 0,00 | J24: 0,00 | K24: 211004 | L24: 211 | M24: =IFERROR(VLOOKUP((OFFSET(hoje12_326_ana9,23,10,1,1)&"."&OFFSET(hoje12_326_ana9,23,11,1,1)),'12.326'!A:D,4,0),"-") -> 12887219000133
A25: 11100987 | B25: CD COLG TT LIMP PROF INTERDENT..01X 90GR | C25: 501.6 | D25: 0 | E25: 48 | F25: 10.45 | G25: 0,00 | H25: 0,00 | I25: 0,00 | J25: 0,00 | K25: 600 | L25: 507 | M25: =IFERROR(VLOOKUP((OFFSET(hoje12_326_ana9,24,10,1,1)&"."&OFFSET(hoje12_326_ana9,24,11,1,1)),'12.326'!A:D,4,0),"-") -> 20335148000275
A26: 11100992 | B26: CD COLG TT LIMP PROF INTERDENT..01X180GR | C26: 736.8 | D26: 0 | E26: 48 | F26: 15.35 | G26: 0,00 | H26: 0,00 | I26: 0,00 | J26: 0,00 | K26: 600 | L26: 507 | M26: =IFERROR(VLOOKUP((OFFSET(hoje12_326_ana9,25,10,1,1)&"."&OFFSET(hoje12_326_ana9,25,11,1,1)),'12.326'!A:D,4,0),"-") -> 20335148000275
A27: 11100998 | B27: CD COLG LUM WHIT COLOR CORRECT..01X133GR | C27: 1080.72 | D27: 0 | E27: 72 | F27: 15.01 | G27: 0,00 | H27: 0,00 | I27: 0,00 | J27: 0,00 | K27: 600 | L27: 507 | M27: =IFERROR(VLOOKUP((OFFSET(hoje12_326_ana9,26,10,1,1)&"."&OFFSET(hoje12_326_ana9,26,11,1,1)),'12.326'!A:D,4,0),"-") -> 20335148000275
A28: 11101000 | B28: ED COLG AD SMILES HARRY POTTER..01X 02UN | C28: 275.88 | D28: 0 | E28: 12 | F28: 22.99 | G28: 0,00 | H28: 0,00 | I28: 0,00 | J28: 0,00 | K28: 600 | L28: 507 | M28: =IFERROR(VLOOKUP((OFFSET(hoje12_326_ana9,27,10,1,1)&"."&OFFSET(hoje12_326_ana9,27,11,1,1)),'12.326'!A:D,4,0),"-") -> 20335148000275
A29: 11101003 | B29: SAB LIQ CORP AMORA BANAN IOGURT.01X250ML | C29: 109.75 | D29: 19.37 | E29: 12 | F29: 10.76 | G29: 0,00 | H29: 15,00 | I29: 0,00 | J29: 19,36- | K29: 600 | L29: 507 | M29: =IFERROR(VLOOKUP((OFFSET(hoje12_326_ana9,28,10,1,1)&"."&OFFSET(hoje12_326_ana9,28,11,1,1)),'12.326'!A:D,4,0),"-") -> 20335148000275
A30: 11101004 | B30: SAB LIQ CORP AMEND ABACAT LEITE.01X250ML | C30: 109.75 | D30: 19.37 | E30: 12 | F30: 10.76 | G30: 0,00 | H30: 15,00 | I30: 0,00 | J30: 19,36- | K30: 600 | L30: 507 | M30: =IFERROR(VLOOKUP((OFFSET(hoje12_326_ana9,29,10,1,1)&"."&OFFSET(hoje12_326_ana9,29,11,1,1)),'12.326'!A:D,4,0),"-") -> 20335148000275
A31: 11100987 | B31: CD COLG TT LIMP PROF INTERDENT..01X 90GR | C31: 501.6 | D31: 0 | E31: 48 | F31: 10.45 | G31: 0,00 | H31: 0,00 | I31: 0,00 | J31: 0,00 | K31: 601 | L31: 507 | M31: =IFERROR(VLOOKUP((OFFSET(hoje12_326_ana9,30,10,1,1)&"."&OFFSET(hoje12_326_ana9,30,11,1,1)),'12.326'!A:D,4,0),"-") -> 20335148000194
A32: 11100992 | B32: CD COLG TT LIMP PROF INTERDENT..01X180GR | C32: 736.8 | D32: 0 | E32: 48 | F32: 15.35 | G32: 0,00 | H32: 0,00 | I32: 0,00 | J32: 0,00 | K32: 601 | L32: 507 | M32: =IFERROR(VLOOKUP((OFFSET(hoje12_326_ana9,31,10,1,1)&"."&OFFSET(hoje12_326_ana9,31,11,1,1)),'12.326'!A:D,4,0),"-") -> 20335148000194
A33: 11100998 | B33: CD COLG LUM WHIT COLOR CORRECT..01X133GR | C33: 1080.72 | D33: 0 | E33: 72 | F33: 15.01 | G33: 0,00 | H33: 0,00 | I33: 0,00 | J33: 0,00 | K33: 601 | L33: 507 | M33: =IFERROR(VLOOKUP((OFFSET(hoje12_326_ana9,32,10,1,1)&"."&OFFSET(hoje12_326_ana9,32,11,1,1)),'12.326'!A:D,4,0),"-") -> 20335148000194
A34: 11101000 | B34: ED COLG AD SMILES HARRY POTTER..01X 02UN | C34: 275.88 | D34: 0 | E34: 12 | F34: 22.99 | G34: 0,00 | H34: 0,00 | I34: 0,00 | J34: 0,00 | K34: 601 | L34: 507 | M34: =IFERROR(VLOOKUP((OFFSET(hoje12_326_ana9,33,10,1,1)&"."&OFFSET(hoje12_326_ana9,33,11,1,1)),'12.326'!A:D,4,0),"-") -> 20335148000194
A35: 11101003 | B35: SAB LIQ CORP AMORA BANAN IOGURT.01X250ML | C35: 109.75 | D35: 19.37 | E35: 12 | F35: 10.76 | G35: 0,00 | H35: 15,00 | I35: 0,00 | J35: 19,36- | K35: 601 | L35: 507 | M35: =IFERROR(VLOOKUP((OFFSET(hoje12_326_ana9,34,10,1,1)&"."&OFFSET(hoje12_326_ana9,34,11,1,1)),'12.326'!A:D,4,0),"-") -> 20335148000194
A36: 11101004 | B36: SAB LIQ CORP AMEND ABACAT LEITE.01X250ML | C36: 109.75 | D36: 19.37 | E36: 12 | F36: 10.76 | G36: 0,00 | H36: 15,00 | I36: 0,00 | J36: 19,36- | K36: 601 | L36: 507 | M36: =IFERROR(VLOOKUP((OFFSET(hoje12_326_ana9,35,10,1,1)&"."&OFFSET(hoje12_326_ana9,35,11,1,1)),'12.326'!A:D,4,0),"-") -> 20335148000194
A37: 11101000 | B37: ED COLG AD SMILES HARRY POTTER..01X 02UN | C37: 68.97 | D37: 0 | E37: 3 | F37: 22.99 | G37: 0,00 | H37: 0,00 | I37: 0,00 | J37: 0,00 | K37: 507001 | L37: 507 | M37: =IFERROR(VLOOKUP((OFFSET(hoje12_326_ana9,36,10,1,1)&"."&OFFSET(hoje12_326_ana9,36,11,1,1)),'12.326'!A:D,4,0),"-") -> 20335148000194
A38: 11100998 | B38: CD COLG LUM WHIT COLOR CORRECT..01X133GR | C38: 45.03 | D38: 0 | E38: 3 | F38: 15.01 | G38: 0,00 | H38: 0,00 | I38: 0,00 | J38: 0,00 | K38: 507001 | L38: 507 | M38: =IFERROR(VLOOKUP((OFFSET(hoje12_326_ana9,37,10,1,1)&"."&OFFSET(hoje12_326_ana9,37,11,1,1)),'12.326'!A:D,4,0),"-") -> 20335148000194
A39: 11101004 | B39: SAB LIQ CORP AMEND ABACAT LEITE.01X250ML | C39: 32.28 | D39: 0 | E39: 3 | F39: 10.76 | G39: 0,00 | H39: 0,00 | I39: 0,00 | J39: 0,00 | K39: 507001 | L39: 507 | M39: =IFERROR(VLOOKUP((OFFSET(hoje12_326_ana9,38,10,1,1)&"."&OFFSET(hoje12_326_ana9,38,11,1,1)),'12.326'!A:D,4,0),"-") -> 20335148000194
A40: 11101003 | B40: SAB LIQ CORP AMORA BANAN IOGURT.01X250ML | C40: 32.28 | D40: 0 | E40: 3 | F40: 10.76 | G40: 0,00 | H40: 0,00 | I40: 0,00 | J40: 0,00 | K40: 507001 | L40: 507 | M40: =IFERROR(VLOOKUP((OFFSET(hoje12_326_ana9,39,10,1,1)&"."&OFFSET(hoje12_326_ana9,39,11,1,1)),'12.326'!A:D,4,0),"-") -> 20335148000194
A41: 11101000 | B41: ED COLG AD SMILES HARRY POTTER..01X 02UN | C41: 68.97 | D41: 0 | E41: 3 | F41: 22.99 | G41: 0,00 | H41: 0,00 | I41: 0,00 | J41: 0,00 | K41: 507002 | L41: 507 | M41: =IFERROR(VLOOKUP((OFFSET(hoje12_326_ana9,40,10,1,1)&"."&OFFSET(hoje12_326_ana9,40,11,1,1)),'12.326'!A:D,4,0),"-") -> 20335148000275
A42: 11100998 | B42: CD COLG LUM WHIT COLOR CORRECT..01X133GR | C42: 45.03 | D42: 0 | E42: 3 | F42: 15.01 | G42: 0,00 | H42: 0,00 | I42: 0,00 | J42: 0,00 | K42: 507002 | L42: 507 | M42: =IFERROR(VLOOKUP((OFFSET(hoje12_326_ana9,41,10,1,1)&"."&OFFSET(hoje12_326_ana9,41,11,1,1)),'12.326'!A:D,4,0),"-") -> 20335148000275
A43: 11101004 | B43: SAB LIQ CORP AMEND ABACAT LEITE.01X250ML | C43: 32.28 | D43: 0 | E43: 3 | F43: 10.76 | G43: 0,00 | H43: 0,00 | I43: 0,00 | J43: 0,00 | K43: 507002 | L43: 507 | M43: =IFERROR(VLOOKUP((OFFSET(hoje12_326_ana9,42,10,1,1)&"."&OFFSET(hoje12_326_ana9,42,11,1,1)),'12.326'!A:D,4,0),"-") -> 20335148000275
A44: 11101003 | B44: SAB LIQ CORP AMORA BANAN IOGURT.01X250ML | C44: 32.28 | D44: 0 | E44: 3 | F44: 10.76 | G44: 0,00 | H44: 0,00 | I44: 0,00 | J44: 0,00 | K44: 507002 | L44: 507 | M44: =IFERROR(VLOOKUP((OFFSET(hoje12_326_ana9,43,10,1,1)&"."&OFFSET(hoje12_326_ana9,43,11,1,1)),'12.326'!A:D,4,0),"-") -> 20335148000275
A45: 11101000 | B45: ED COLG AD SMILES HARRY POTTER..01X 02UN | C45: 68.97 | D45: 0 | E45: 3 | F45: 22.99 | G45: 0,00 | H45: 0,00 | I45: 0,00 | J45: 0,00 | K45: 507003 | L45: 507 | M45: =IFERROR(VLOOKUP((OFFSET(hoje12_326_ana9,44,10,1,1)&"."&OFFSET(hoje12_326_ana9,44,11,1,1)),'12.326'!A:D,4,0),"-") -> 4757459000519
A46: 11100998 | B46: CD COLG LUM WHIT COLOR CORRECT..01X133GR | C46: 45.03 | D46: 0 | E46: 3 | F46: 15.01 | G46: 0,00 | H46: 0,00 | I46: 0,00 | J46: 0,00 | K46: 507003 | L46: 507 | M46: =IFERROR(VLOOKUP((OFFSET(hoje12_326_ana9,45,10,1,1)&"."&OFFSET(hoje12_326_ana9,45,11,1,1)),'12.326'!A:D,4,0),"-") -> 4757459000519
A47: 11101004 | B47: SAB LIQ CORP AMEND ABACAT LEITE.01X250ML | C47: 32.28 | D47: 0 | E47: 3 | F47: 10.76 | G47: 0,00 | H47: 0,00 | I47: 0,00 | J47: 0,00 | K47: 507003 | L47: 507 | M47: =IFERROR(VLOOKUP((OFFSET(hoje12_326_ana9,46,10,1,1)&"."&OFFSET(hoje12_326_ana9,46,11,1,1)),'12.326'!A:D,4,0),"-") -> 4757459000519
A48: 11101003 | B48: SAB LIQ CORP AMORA BANAN IOGURT.01X250ML | C48: 32.28 | D48: 0 | E48: 3 | F48: 10.76 | G48: 0,00 | H48: 0,00 | I48: 0,00 | J48: 0,00 | K48: 507003 | L48: 507 | M48: =IFERROR(VLOOKUP((OFFSET(hoje12_326_ana9,47,10,1,1)&"."&OFFSET(hoje12_326_ana9,47,11,1,1)),'12.326'!A:D,4,0),"-") -> 4757459000519
A49: 11100988 | B49: COND DARLING CACHOS.............01X315ML | C49: 37.26 | D49: 4.14 | E49: 6 | F49: 6.9 | G49: 0,00 | H49: 10,00 | I49: 0,00 | J49: 4,14- | K49: 1240 | L49: 702 | M49: =IFERROR(VLOOKUP((OFFSET(hoje12_326_ana9,48,10,1,1)&"."&OFFSET(hoje12_326_ana9,48,11,1,1)),'12.326'!A:D,4,0),"-") -> 35831943000140
A50: 11100995 | B50: CD COLG SMILES INF HARRY POTTER.01X100GR | C50: 89.04 | D50: 0 | E50: 6 | F50: 14.84 | G50: 0,00 | H50: 0,00 | I50: 0,00 | J50: 0,00 | K50: 1240 | L50: 702 | M50: =IFERROR(VLOOKUP((OFFSET(hoje12_326_ana9,49,10,1,1)&"."&OFFSET(hoje12_326_ana9,49,11,1,1)),'12.326'!A:D,4,0),"-") -> 35831943000140
A51: 11100998 | B51: CD COLG LUM WHIT COLOR CORRECT..01X133GR | C51: 180.12 | D51: 0 | E51: 12 | F51: 15.01 | G51: 0,00 | H51: 0,00 | I51: 0,00 | J51: 0,00 | K51: 1240 | L51: 702 | M51: =IFERROR(VLOOKUP((OFFSET(hoje12_326_ana9,50,10,1,1)&"."&OFFSET(hoje12_326_ana9,50,11,1,1)),'12.326'!A:D,4,0),"-") -> 35831943000140
A52: 11100987 | B52: CD COLG TT LIMP PROF INTERDENT..01X 90GR | C52: 250.8 | D52: 0 | E52: 24 | F52: 10.45 | G52: 0,00 | H52: 0,00 | I52: 0,00 | J52: 0,00 | K52: 1240 | L52: 702 | M52: =IFERROR(VLOOKUP((OFFSET(hoje12_326_ana9,51,10,1,1)&"."&OFFSET(hoje12_326_ana9,51,11,1,1)),'12.326'!A:D,4,0),"-") -> 35831943000140
A53: 11100993 | B53: SAB LIQ PALM OIL ABAC IRIS P ES.01X200ML | C53: 22.1 | D53: 3.9 | E53: 4 | F53: 6.5 | G53: 0,00 | H53: 15,00 | I53: 0,00 | J53: 3,90- | K53: 1240 | L53: 702 | M53: =IFERROR(VLOOKUP((OFFSET(hoje12_326_ana9,52,10,1,1)&"."&OFFSET(hoje12_326_ana9,52,11,1,1)),'12.326'!A:D,4,0),"-") -> 35831943000140
A54: 11100990 | B54: SAB LIQ PALM LUM OIL FIGO ORQUI.01X200ML | C54: 22.1 | D54: 3.9 | E54: 4 | F54: 6.5 | G54: 0,00 | H54: 15,00 | I54: 0,00 | J54: 3,90- | K54: 1240 | L54: 702 | M54: =IFERROR(VLOOKUP((OFFSET(hoje12_326_ana9,53,10,1,1)&"."&OFFSET(hoje12_326_ana9,53,11,1,1)),'12.326'!A:D,4,0),"-") -> 35831943000140
A55: 11101003 | B55: SAB LIQ CORP AMORA BANAN IOGURT.01X250ML | C55: 54.88 | D55: 9.68 | E55: 6 | F55: 10.76 | G55: 0,00 | H55: 15,00 | I55: 0,00 | J55: 9,68- | K55: 1240 | L55: 702 | M55: =IFERROR(VLOOKUP((OFFSET(hoje12_326_ana9,54,10,1,1)&"."&OFFSET(hoje12_326_ana9,54,11,1,1)),'12.326'!A:D,4,0),"-") -> 35831943000140
A56: 11101004 | B56: SAB LIQ CORP AMEND ABACAT LEITE.01X250ML | C56: 54.88 | D56: 9.68 | E56: 6 | F56: 10.76 | G56: 0,00 | H56: 15,00 | I56: 0,00 | J56: 9,68- | K56: 1240 | L56: 702 | M56: =IFERROR(VLOOKUP((OFFSET(hoje12_326_ana9,55,10,1,1)&"."&OFFSET(hoje12_326_ana9,55,11,1,1)),'12.326'!A:D,4,0),"-") -> 35831943000140
A57: 11100986 | B57: SAB LIQ PROTEX ERV DOCE RF LMPM.01X500ML | C57: 44.01 | D57: 7.77 | E57: 3 | F57: 17.26 | G57: 0,00 | H57: 15,00 | I57: 0,00 | J57: 7,76- | K57: 1240 | L57: 702 | M57: =IFERROR(VLOOKUP((OFFSET(hoje12_326_ana9,56,10,1,1)&"."&OFFSET(hoje12_326_ana9,56,11,1,1)),'12.326'!A:D,4,0),"-") -> 35831943000140
A58: 11100989 | B58: SH DARLING CACHOS...............01X315ML | C58: 35.53 | D58: 3.95 | E58: 6 | F58: 6.58 | G58: 0,00 | H58: 10,00 | I58: 0,00 | J58: 3,94- | K58: 1240 | L58: 702 | M58: =IFERROR(VLOOKUP((OFFSET(hoje12_326_ana9,57,10,1,1)&"."&OFFSET(hoje12_326_ana9,57,11,1,1)),'12.326'!A:D,4,0),"-") -> 35831943000140
A59: 11100988 | B59: COND DARLING CACHOS.............01X315ML | C59: 37.26 | D59: 4.14 | E59: 6 | F59: 6.9 | G59: 0,00 | H59: 10,00 | I59: 0,00 | J59: 4,14- | K59: 1241 | L59: 702 | M59: =IFERROR(VLOOKUP((OFFSET(hoje12_326_ana9,58,10,1,1)&"."&OFFSET(hoje12_326_ana9,58,11,1,1)),'12.326'!A:D,4,0),"-") -> 35831943000302
A60: 11100995 | B60: CD COLG SMILES INF HARRY POTTER.01X100GR | C60: 89.04 | D60: 0 | E60: 6 | F60: 14.84 | G60: 0,00 | H60: 0,00 | I60: 0,00 | J60: 0,00 | K60: 1241 | L60: 702 | M60: =IFERROR(VLOOKUP((OFFSET(hoje12_326_ana9,59,10,1,1)&"."&OFFSET(hoje12_326_ana9,59,11,1,1)),'12.326'!A:D,4,0),"-") -> 35831943000302
A61: 11100998 | B61: CD COLG LUM WHIT COLOR CORRECT..01X133GR | C61: 180.12 | D61: 0 | E61: 12 | F61: 15.01 | G61: 0,00 | H61: 0,00 | I61: 0,00 | J61: 0,00 | K61: 1241 | L61: 702 | M61: =IFERROR(VLOOKUP((OFFSET(hoje12_326_ana9,60,10,1,1)&"."&OFFSET(hoje12_326_ana9,60,11,1,1)),'12.326'!A:D,4,0),"-") -> 35831943000302
A62: 11100987 | B62: CD COLG TT LIMP PROF INTERDENT..01X 90GR | C62: 250.8 | D62: 0 | E62: 24 | F62: 10.45 | G62: 0,00 | H62: 0,00 | I62: 0,00 | J62: 0,00 | K62: 1241 | L62: 702 | M62: =IFERROR(VLOOKUP((OFFSET(hoje12_326_ana9,61,10,1,1)&"."&OFFSET(hoje12_326_ana9,61,11,1,1)),'12.326'!A:D,4,0),"-") -> 35831943000302
A63: 11100993 | B63: SAB LIQ PALM OIL ABAC IRIS P ES.01X200ML | C63: 22.1 | D63: 3.9 | E63: 4 | F63: 6.5 | G63: 0,00 | H63: 15,00 | I63: 0,00 | J63: 3,90- | K63: 1241 | L63: 702 | M63: =IFERROR(VLOOKUP((OFFSET(hoje12_326_ana9,62,10,1,1)&"."&OFFSET(hoje12_326_ana9,62,11,1,1)),'12.326'!A:D,4,0),"-") -> 35831943000302
A64: 11100990 | B64: SAB LIQ PALM LUM OIL FIGO ORQUI.01X200ML | C64: 22.1 | D64: 3.9 | E64: 4 | F64: 6.5 | G64: 0,00 | H64: 15,00 | I64: 0,00 | J64: 3,90- | K64: 1241 | L64: 702 | M64: =IFERROR(VLOOKUP((OFFSET(hoje12_326_ana9,63,10,1,1)&"."&OFFSET(hoje12_326_ana9,63,11,1,1)),'12.326'!A:D,4,0),"-") -> 35831943000302
A65: 11101003 | B65: SAB LIQ CORP AMORA BANAN IOGURT.01X250ML | C65: 54.88 | D65: 9.68 | E65: 6 | F65: 10.76 | G65: 0,00 | H65: 15,00 | I65: 0,00 | J65: 9,68- | K65: 1241 | L65: 702 | M65: =IFERROR(VLOOKUP((OFFSET(hoje12_326_ana9,64,10,1,1)&"."&OFFSET(hoje12_326_ana9,64,11,1,1)),'12.326'!A:D,4,0),"-") -> 35831943000302
A66: 11101004 | B66: SAB LIQ CORP AMEND ABACAT LEITE.01X250ML | C66: 54.88 | D66: 9.68 | E66: 6 | F66: 10.76 | G66: 0,00 | H66: 15,00 | I66: 0,00 | J66: 9,68- | K66: 1241 | L66: 702 | M66: =IFERROR(VLOOKUP((OFFSET(hoje12_326_ana9,65,10,1,1)&"."&OFFSET(hoje12_326_ana9,65,11,1,1)),'12.326'!A:D,4,0),"-") -> 35831943000302
A67: 11100986 | B67: SAB LIQ PROTEX ERV DOCE RF LMPM.01X500ML | C67: 44.01 | D67: 7.77 | E67: 3 | F67: 17.26 | G67: 0,00 | H67: 15,00 | I67: 0,00 | J67: 7,76- | K67: 1241 | L67: 702 | M67: =IFERROR(VLOOKUP((OFFSET(hoje12_326_ana9,66,10,1,1)&"."&OFFSET(hoje12_326_ana9,66,11,1,1)),'12.326'!A:D,4,0),"-") -> 35831943000302
A68: 11100989 | B68: SH DARLING CACHOS...............01X315ML | C68: 35.53 | D68: 3.95 | E68: 6 | F68: 6.58 | G68: 0,00 | H68: 10,00 | I68: 0,00 | J68: 3,94- | K68: 1241 | L68: 702 | M68: =IFERROR(VLOOKUP((OFFSET(hoje12_326_ana9,67,10,1,1)&"."&OFFSET(hoje12_326_ana9,67,11,1,1)),'12.326'!A:D,4,0),"-") -> 35831943000302
A69: 11100988 | B69: COND DARLING CACHOS.............01X315ML | C69: 37.26 | D69: 4.14 | E69: 6 | F69: 6.9 | G69: 0,00 | H69: 10,00 | I69: 0,00 | J69: 4,14- | K69: 1242 | L69: 702 | M69: =IFERROR(VLOOKUP((OFFSET(hoje12_326_ana9,68,10,1,1)&"."&OFFSET(hoje12_326_ana9,68,11,1,1)),'12.326'!A:D,4,0),"-") -> 35831943000493
A70: 11100995 | B70: CD COLG SMILES INF HARRY POTTER.01X100GR | C70: 89.04 | D70: 0 | E70: 6 | F70: 14.84 | G70: 0,00 | H70: 0,00 | I70: 0,00 | J70: 0,00 | K70: 1242 | L70: 702 | M70: =IFERROR(VLOOKUP((OFFSET(hoje12_326_ana9,69,10,1,1)&"."&OFFSET(hoje12_326_ana9,69,11,1,1)),'12.326'!A:D,4,0),"-") -> 35831943000493
A71: 11100998 | B71: CD COLG LUM WHIT COLOR CORRECT..01X133GR | C71: 180.12 | D71: 0 | E71: 12 | F71: 15.01 | G71: 0,00 | H71: 0,00 | I71: 0,00 | J71: 0,00 | K71: 1242 | L71: 702 | M71: =IFERROR(VLOOKUP((OFFSET(hoje12_326_ana9,70,10,1,1)&"."&OFFSET(hoje12_326_ana9,70,11,1,1)),'12.326'!A:D,4,0),"-") -> 35831943000493
A72: 11100987 | B72: CD COLG TT LIMP PROF INTERDENT..01X 90GR | C72: 250.8 | D72: 0 | E72: 24 | F72: 10.45 | G72: 0,00 | H72: 0,00 | I72: 0,00 | J72: 0,00 | K72: 1242 | L72: 702 | M72: =IFERROR(VLOOKUP((OFFSET(hoje12_326_ana9,71,10,1,1)&"."&OFFSET(hoje12_326_ana9,71,11,1,1)),'12.326'!A:D,4,0),"-") -> 35831943000493
A73: 11100993 | B73: SAB LIQ PALM OIL ABAC IRIS P ES.01X200ML | C73: 22.1 | D73: 3.9 | E73: 4 | F73: 6.5 | G73: 0,00 | H73: 15,00 | I73: 0,00 | J73: 3,90- | K73: 1242 | L73: 702 | M73: =IFERROR(VLOOKUP((OFFSET(hoje12_326_ana9,72,10,1,1)&"."&OFFSET(hoje12_326_ana9,72,11,1,1)),'12.326'!A:D,4,0),"-") -> 35831943000493
A74: 11100990 | B74: SAB LIQ PALM LUM OIL FIGO ORQUI.01X200ML | C74: 22.1 | D74: 3.9 | E74: 4 | F74: 6.5 | G74: 0,00 | H74: 15,00 | I74: 0,00 | J74: 3,90- | K74: 1242 | L74: 702 | M74: =IFERROR(VLOOKUP((OFFSET(hoje12_326_ana9,73,10,1,1)&"."&OFFSET(hoje12_326_ana9,73,11,1,1)),'12.326'!A:D,4,0),"-") -> 35831943000493
A75: 11101003 | B75: SAB LIQ CORP AMORA BANAN IOGURT.01X250ML | C75: 54.88 | D75: 9.68 | E75: 6 | F75: 10.76 | G75: 0,00 | H75: 15,00 | I75: 0,00 | J75: 9,68- | K75: 1242 | L75: 702 | M75: =IFERROR(VLOOKUP((OFFSET(hoje12_326_ana9,74,10,1,1)&"."&OFFSET(hoje12_326_ana9,74,11,1,1)),'12.326'!A:D,4,0),"-") -> 35831943000493
A76: 11101004 | B76: SAB LIQ CORP AMEND ABACAT LEITE.01X250ML | C76: 54.88 | D76: 9.68 | E76: 6 | F76: 10.76 | G76: 0,00 | H76: 15,00 | I76: 0,00 | J76: 9,68- | K76: 1242 | L76: 702 | M76: =IFERROR(VLOOKUP((OFFSET(hoje12_326_ana9,75,10,1,1)&"."&OFFSET(hoje12_326_ana9,75,11,1,1)),'12.326'!A:D,4,0),"-") -> 35831943000493
A77: 11100986 | B77: SAB LIQ PROTEX ERV DOCE RF LMPM.01X500ML | C77: 44.01 | D77: 7.77 | E77: 3 | F77: 17.26 | G77: 0,00 | H77: 15,00 | I77: 0,00 | J77: 7,76- | K77: 1242 | L77: 702 | M77: =IFERROR(VLOOKUP((OFFSET(hoje12_326_ana9,76,10,1,1)&"."&OFFSET(hoje12_326_ana9,76,11,1,1)),'12.326'!A:D,4,0),"-") -> 35831943000493
A78: 11100989 | B78: SH DARLING CACHOS...............01X315ML | C78: 35.53 | D78: 3.95 | E78: 6 | F78: 6.58 | G78: 0,00 | H78: 10,00 | I78: 0,00 | J78: 3,94- | K78: 1242 | L78: 702 | M78: =IFERROR(VLOOKUP((OFFSET(hoje12_326_ana9,77,10,1,1)&"."&OFFSET(hoje12_326_ana9,77,11,1,1)),'12.326'!A:D,4,0),"-") -> 35831943000493
A79: 11100988 | B79: COND DARLING CACHOS.............01X315ML | C79: 37.26 | D79: 4.14 | E79: 6 | F79: 6.9 | G79: 0,00 | H79: 10,00 | I79: 0,00 | J79: 4,14- | K79: 1243 | L79: 702 | M79: =IFERROR(VLOOKUP((OFFSET(hoje12_326_ana9,78,10,1,1)&"."&OFFSET(hoje12_326_ana9,78,11,1,1)),'12.326'!A:D,4,0),"-") -> 35831943000574
A80: 11100995 | B80: CD COLG SMILES INF HARRY POTTER.01X100GR | C80: 89.04 | D80: 0 | E80: 6 | F80: 14.84 | G80: 0,00 | H80: 0,00 | I80: 0,00 | J80: 0,00 | K80: 1243 | L80: 702 | M80: =IFERROR(VLOOKUP((OFFSET(hoje12_326_ana9,79,10,1,1)&"."&OFFSET(hoje12_326_ana9,79,11,1,1)),'12.326'!A:D,4,0),"-") -> 35831943000574
A81: 11100998 | B81: CD COLG LUM WHIT COLOR CORRECT..01X133GR | C81: 180.12 | D81: 0 | E81: 12 | F81: 15.01 | G81: 0,00 | H81: 0,00 | I81: 0,00 | J81: 0,00 | K81: 1243 | L81: 702 | M81: =IFERROR(VLOOKUP((OFFSET(hoje12_326_ana9,80,10,1,1)&"."&OFFSET(hoje12_326_ana9,80,11,1,1)),'12.326'!A:D,4,0),"-") -> 35831943000574
A82: 11100987 | B82: CD COLG TT LIMP PROF INTERDENT..01X 90GR | C82: 250.8 | D82: 0 | E82: 24 | F82: 10.45 | G82: 0,00 | H82: 0,00 | I82: 0,00 | J82: 0,00 | K82: 1243 | L82: 702 | M82: =IFERROR(VLOOKUP((OFFSET(hoje12_326_ana9,81,10,1,1)&"."&OFFSET(hoje12_326_ana9,81,11,1,1)),'12.326'!A:D,4,0),"-") -> 35831943000574
A83: 11100993 | B83: SAB LIQ PALM OIL ABAC IRIS P ES.01X200ML | C83: 22.1 | D83: 3.9 | E83: 4 | F83: 6.5 | G83: 0,00 | H83: 15,00 | I83: 0,00 | J83: 3,90- | K83: 1243 | L83: 702 | M83: =IFERROR(VLOOKUP((OFFSET(hoje12_326_ana9,82,10,1,1)&"."&OFFSET(hoje12_326_ana9,82,11,1,1)),'12.326'!A:D,4,0),"-") -> 35831943000574
A84: 11100990 | B84: SAB LIQ PALM LUM OIL FIGO ORQUI.01X200ML | C84: 22.1 | D84: 3.9 | E84: 4 | F84: 6.5 | G84: 0,00 | H84: 15,00 | I84: 0,00 | J84: 3,90- | K84: 1243 | L84: 702 | M84: =IFERROR(VLOOKUP((OFFSET(hoje12_326_ana9,83,10,1,1)&"."&OFFSET(hoje12_326_ana9,83,11,1,1)),'12.326'!A:D,4,0),"-") -> 35831943000574
A85: 11101003 | B85: SAB LIQ CORP AMORA BANAN IOGURT.01X250ML | C85: 54.88 | D85: 9.68 | E85: 6 | F85: 10.76 | G85: 0,00 | H85: 15,00 | I85: 0,00 | J85: 9,68- | K85: 1243 | L85: 702 | M85: =IFERROR(VLOOKUP((OFFSET(hoje12_326_ana9,84,10,1,1)&"."&OFFSET(hoje12_326_ana9,84,11,1,1)),'12.326'!A:D,4,0),"-") -> 35831943000574
A86: 11101004 | B86: SAB LIQ CORP AMEND ABACAT LEITE.01X250ML | C86: 54.88 | D86: 9.68 | E86: 6 | F86: 10.76 | G86: 0,00 | H86: 15,00 | I86: 0,00 | J86: 9,68- | K86: 1243 | L86: 702 | M86: =IFERROR(VLOOKUP((OFFSET(hoje12_326_ana9,85,10,1,1)&"."&OFFSET(hoje12_326_ana9,85,11,1,1)),'12.326'!A:D,4,0),"-") -> 35831943000574
A87: 11100986 | B87: SAB LIQ PROTEX ERV DOCE RF LMPM.01X500ML | C87: 44.01 | D87: 7.77 | E87: 3 | F87: 17.26 | G87: 0,00 | H87: 15,00 | I87: 0,00 | J87: 7,76- | K87: 1243 | L87: 702 | M87: =IFERROR(VLOOKUP((OFFSET(hoje12_326_ana9,86,10,1,1)&"."&OFFSET(hoje12_326_ana9,86,11,1,1)),'12.326'!A:D,4,0),"-") -> 35831943000574
A88: 11100989 | B88: SH DARLING CACHOS...............01X315ML | C88: 35.53 | D88: 3.95 | E88: 6 | F88: 6.58 | G88: 0,00 | H88: 10,00 | I88: 0,00 | J88: 3,94- | K88: 1243 | L88: 702 | M88: =IFERROR(VLOOKUP((OFFSET(hoje12_326_ana9,87,10,1,1)&"."&OFFSET(hoje12_326_ana9,87,11,1,1)),'12.326'!A:D,4,0),"-") -> 35831943000574
A89: 11100988 | B89: COND DARLING CACHOS.............01X315ML | C89: 37.26 | D89: 4.14 | E89: 6 | F89: 6.9 | G89: 0,00 | H89: 10,00 | I89: 0,00 | J89: 4,14- | K89: 1244 | L89: 702 | M89: =IFERROR(VLOOKUP((OFFSET(hoje12_326_ana9,88,10,1,1)&"."&OFFSET(hoje12_326_ana9,88,11,1,1)),'12.326'!A:D,4,0),"-") -> 35831943000736
A90: 11100995 | B90: CD COLG SMILES INF HARRY POTTER.01X100GR | C90: 89.04 | D90: 0 | E90: 6 | F90: 14.84 | G90: 0,00 | H90: 0,00 | I90: 0,00 | J90: 0,00 | K90: 1244 | L90: 702 | M90: =IFERROR(VLOOKUP((OFFSET(hoje12_326_ana9,89,10,1,1)&"."&OFFSET(hoje12_326_ana9,89,11,1,1)),'12.326'!A:D,4,0),"-") -> 35831943000736
A91: 11100998 | B91: CD COLG LUM WHIT COLOR CORRECT..01X133GR | C91: 180.12 | D91: 0 | E91: 12 | F91: 15.01 | G91: 0,00 | H91: 0,00 | I91: 0,00 | J91: 0,00 | K91: 1244 | L91: 702 | M91: =IFERROR(VLOOKUP((OFFSET(hoje12_326_ana9,90,10,1,1)&"."&OFFSET(hoje12_326_ana9,90,11,1,1)),'12.326'!A:D,4,0),"-") -> 35831943000736
A92: 11100987 | B92: CD COLG TT LIMP PROF INTERDENT..01X 90GR | C92: 125.4 | D92: 0 | E92: 12 | F92: 10.45 | G92: 0,00 | H92: 0,00 | I92: 0,00 | J92: 0,00 | K92: 1244 | L92: 702 | M92: =IFERROR(VLOOKUP((OFFSET(hoje12_326_ana9,91,10,1,1)&"."&OFFSET(hoje12_326_ana9,91,11,1,1)),'12.326'!A:D,4,0),"-") -> 35831943000736
A93: 11100993 | B93: SAB LIQ PALM OIL ABAC IRIS P ES.01X200ML | C93: 22.1 | D93: 3.9 | E93: 4 | F93: 6.5 | G93: 0,00 | H93: 15,00 | I93: 0,00 | J93: 3,90- | K93: 1244 | L93: 702 | M93: =IFERROR(VLOOKUP((OFFSET(hoje12_326_ana9,92,10,1,1)&"."&OFFSET(hoje12_326_ana9,92,11,1,1)),'12.326'!A:D,4,0),"-") -> 35831943000736
A94: 11100990 | B94: SAB LIQ PALM LUM OIL FIGO ORQUI.01X200ML | C94: 22.1 | D94: 3.9 | E94: 4 | F94: 6.5 | G94: 0,00 | H94: 15,00 | I94: 0,00 | J94: 3,90- | K94: 1244 | L94: 702 | M94: =IFERROR(VLOOKUP((OFFSET(hoje12_326_ana9,93,10,1,1)&"."&OFFSET(hoje12_326_ana9,93,11,1,1)),'12.326'!A:D,4,0),"-") -> 35831943000736
A95: 11101003 | B95: SAB LIQ CORP AMORA BANAN IOGURT.01X250ML | C95: 54.88 | D95: 9.68 | E95: 6 | F95: 10.76 | G95: 0,00 | H95: 15,00 | I95: 0,00 | J95: 9,68- | K95: 1244 | L95: 702 | M95: =IFERROR(VLOOKUP((OFFSET(hoje12_326_ana9,94,10,1,1)&"."&OFFSET(hoje12_326_ana9,94,11,1,1)),'12.326'!A:D,4,0),"-") -> 35831943000736
A96: 11101004 | B96: SAB LIQ CORP AMEND ABACAT LEITE.01X250ML | C96: 54.88 | D96: 9.68 | E96: 6 | F96: 10.76 | G96: 0,00 | H96: 15,00 | I96: 0,00 | J96: 9,68- | K96: 1244 | L96: 702 | M96: =IFERROR(VLOOKUP((OFFSET(hoje12_326_ana9,95,10,1,1)&"."&OFFSET(hoje12_326_ana9,95,11,1,1)),'12.326'!A:D,4,0),"-") -> 35831943000736
A97: 11100986 | B97: SAB LIQ PROTEX ERV DOCE RF LMPM.01X500ML | C97: 44.01 | D97: 7.77 | E97: 3 | F97: 17.26 | G97: 0,00 | H97: 15,00 | I97: 0,00 | J97: 7,76- | K97: 1244 | L97: 702 | M97: =IFERROR(VLOOKUP((OFFSET(hoje12_326_ana9,96,10,1,1)&"."&OFFSET(hoje12_326_ana9,96,11,1,1)),'12.326'!A:D,4,0),"-") -> 35831943000736
A98: 11100989 | B98: SH DARLING CACHOS...............01X315ML | C98: 35.53 | D98: 3.95 | E98: 6 | F98: 6.58 | G98: 0,00 | H98: 10,00 | I98: 0,00 | J98: 3,94- | K98: 1244 | L98: 702 | M98: =IFERROR(VLOOKUP((OFFSET(hoje12_326_ana9,97,10,1,1)&"."&OFFSET(hoje12_326_ana9,97,11,1,1)),'12.326'!A:D,4,0),"-") -> 35831943000736
A99: 11100988 | B99: COND DARLING CACHOS.............01X315ML | C99: 37.26 | D99: 4.14 | E99: 6 | F99: 6.9 | G99: 0,00 | H99: 10,00 | I99: 0,00 | J99: 4,14- | K99: 1245 | L99: 702 | M99: =IFERROR(VLOOKUP((OFFSET(hoje12_326_ana9,98,10,1,1)&"."&OFFSET(hoje12_326_ana9,98,11,1,1)),'12.326'!A:D,4,0),"-") -> 35831943000906
A100: 11100995 | B100: CD COLG SMILES INF HARRY POTTER.01X100GR | C100: 89.04 | D100: 0 | E100: 6 | F100: 14.84 | G100: 0,00 | H100: 0,00 | I100: 0,00 | J100: 0,00 | K100: 1245 | L100: 702 | M100: =IFERROR(VLOOKUP((OFFSET(hoje12_326_ana9,99,10,1,1)&"."&OFFSET(hoje12_326_ana9,99,11,1,1)),'12.326'!A:D,4,0),"-") -> 35831943000906
...

Sheet Loja a Loja
F1: =SUBTOTAL(9,F3:F886) -> 50037180 | G1: =SUBTOTAL(9,G3:G886) -> 3438308.1
A2: CNPJ | B2: Razao | C2: Rede | D2: Fantasia | E2: Cidade | F2: META | G2: REALIZADO
A3: 1274396000128 | B3: DAMASCENO E DAMASCENO LTDA | C3: REDE DAMASCENO-PORTAL/PRINCESA | D3: SUPERMERCADOS PRINCESA I | E3: AQUIDAUANA | F3: =VLOOKUP(C3,'Top Redes'!A:D,4,0) -> 119452.2 | G3: =IFERROR(VLOOKUP($A3,'319'!$B:$H,7,0),0) -> 2692.15
A4: 1274396000209 | B4: DAMASCENO E DAMASCENO LTDA | C4: REDE DAMASCENO-PORTAL/PRINCESA | D4: SUPERMERCADOS PRINCESAS II | E4: ANASTACIO | F4: =VLOOKUP(C4,'Top Redes'!A:D,4,0) -> 119452.2 | G4: =IFERROR(VLOOKUP($A4,'319'!$B:$H,7,0),0) -> 4037.09
A5: 1274396000390 | B5: DAMASCENO E DAMASCENO LTDA | C5: REDE DAMASCENO-PORTAL/PRINCESA | D5: SM PRINCESA III | E5: AQUIDAUANA | F5: =VLOOKUP(C5,'Top Redes'!A:D,4,0) -> 119452.2 | G5: =IFERROR(VLOOKUP($A5,'319'!$B:$H,7,0),0) -> 15137.6
A6: 1274396000470 | B6: DAMASCENO E DAMASCENO LTDA | C6: REDE DAMASCENO-PORTAL/PRINCESA | D6: SUPERMERCADO PRINCESA | E6: MIRANDA | F6: =VLOOKUP(C6,'Top Redes'!A:D,4,0) -> 119452.2 | G6: =IFERROR(VLOOKUP($A6,'319'!$B:$H,7,0),0) -> 204.87
A7: 1274396000632 | B7: DAMASCENO E DAMASCENO LTDA | C7: REDE DAMASCENO-PORTAL/PRINCESA | D7: PORTAL ATACADO | E7: ANASTACIO | F7: =VLOOKUP(C7,'Top Redes'!A:D,4,0) -> 119452.2 | G7: =IFERROR(VLOOKUP($A7,'319'!$B:$H,7,0),0) -> 49122.34
A8: 1274396000713 | B8: DAMASCENO E DAMASCENO LTDA | C8: REDE DAMASCENO-PORTAL/PRINCESA | D8: SUPERMERCADOS PRINCESA | E8: MIRANDA | F8: =VLOOKUP(C8,'Top Redes'!A:D,4,0) -> 119452.2 | G8: =IFERROR(VLOOKUP($A8,'319'!$B:$H,7,0),0) -> 7357.77
A9: 1274396000802 | B9: DAMASCENO E DAMASCENO LTDA | C9: REDE DAMASCENO-PORTAL/PRINCESA | D9: SUPERMERCADOS PRINCESA | E9: CHAPADAO DO SUL | F9: =VLOOKUP(C9,'Top Redes'!A:D,4,0) -> 119452.2 | G9: =IFERROR(VLOOKUP($A9,'319'!$B:$H,7,0),0) -> 9335.77
A10: 1274396000985 | B10: DAMASCENO E DAMASCENO LTDA | C10: REDE DAMASCENO-PORTAL/PRINCESA | D10: DAMASCENO E DAMASCENO LTDA | E10: MIRANDA | F10: =VLOOKUP(C10,'Top Redes'!A:D,4,0) -> 119452.2 | G10: =IFERROR(VLOOKUP($A10,'319'!$B:$H,7,0),0) -> 12951.56
A11: 1274396001019 | B11: DAMASCENO E DAMASCENO LTDA | C11: REDE DAMASCENO-PORTAL/PRINCESA | D11: PORTAL ATACADO | E11: AQUIDAUANA | F11: =VLOOKUP(C11,'Top Redes'!A:D,4,0) -> 119452.2 | G11: =IFERROR(VLOOKUP($A11,'319'!$B:$H,7,0),0) -> 35735.35
A12: 2318826000129 | B12: VRA COMERCIO LTDA | C12: REDE VRA / MEGA | D12: SM VERATTI - LJ01 | E12: COSTA RICA | F12: =VLOOKUP(C12,'Top Redes'!A:D,4,0) -> 624018.3 | G12: =IFERROR(VLOOKUP($A12,'319'!$B:$H,7,0),0) -> 40129.08
A13: 2318826000200 | B13: VRA COMERCIO LTDA | C13: REDE VRA / MEGA | D13: MEGA ATACADISTA LJ2 | E13: CORUMBA | F13: =VLOOKUP(C13,'Top Redes'!A:D,4,0) -> 624018.3 | G13: =IFERROR(VLOOKUP($A13,'319'!$B:$H,7,0),0) -> 221339.41
A14: 2318826000390 | B14: VRA COMERCIO LTDA | C14: REDE VRA / MEGA | D14: SM VERATTI - LJ53 | E14: IVINHEMA | F14: =VLOOKUP(C14,'Top Redes'!A:D,4,0) -> 624018.3 | G14: =IFERROR(VLOOKUP($A14,'319'!$B:$H,7,0),0) -> 64515.33
... A160: 46876542000204 | B160: SUPERMERCADO FERNANDES PRODUTOS ALIMENTI | C160: REDE SUP FERNANDES F | D160: FERNANDES SUPERMERCADO | E160: LADARIO | F160: =VLOOKUP(C160,'Top Redes'!A:D,4,0) -> 27961.821 | G160: =IFERROR(VLOOKUP($A160,'319'!$B:$H,7,0),0) -> 7051.11

Sheet redes
A1: CNPJ | B1: Razao | C1: Cidade | D1: Rede | E1: Fantasia | F1: VALOR | G1: A FATURAR
A2: 1178113 | B2: JOICE MOTTA MENDES | C2: CAMPO GRANDE | E2: CONVENIENCIA SERVE MAIS | F2: =IFERROR(VLOOKUP($A2,'319'!$B:$H,7,0),0) -> 0 | G2: =SUMIFS('12.326ana'!$C:$C,'12.326ana'!$M:$M,redes!A2) -> 0
A3: 6498132 | B3: GUSTAVO LORENTZ NEIVA | C3: CAMPO GRANDE | E3: GUGU | F3: =IFERROR(VLOOKUP($A3,'319'!$B:$H,7,0),0) -> 0 | G3: =SUMIFS('12.326ana'!$C:$C,'12.326ana'!$M:$M,redes!A3) -> 0
A4: 8442843 | B4: ALMEIZINO BARBOSA DE SOUZA | C4: CAMPO GRANDE | E4: PANIFICADORA BARBOSA | F4: =IFERROR(VLOOKUP($A4,'319'!$B:$H,7,0),0) -> 0 | G4: =SUMIFS('12.326ana'!$C:$C,'12.326ana'!$M:$M,redes!A4) -> 0
A5: 24921130 | B5: HEMERSON MATHEUS CHIELI | C5: CORUMBA | E5: MERCADO CHIELI | F5: =IFERROR(VLOOKUP($A5,'319'!$B:$H,7,0),0) -> 0 | G5: =SUMIFS('12.326ana'!$C:$C,'12.326ana'!$M:$M,redes!A5) -> 0
A6: 29174163 | B6: ELIAS LONGO JUNIOR | C6: CAMPO GRANDE | E6: ESQUINA DO FRANGO | F6: =IFERROR(VLOOKUP($A6,'319'!$B:$H,7,0),0) -> 0 | G6: =SUMIFS('12.326ana'!$C:$C,'12.326ana'!$M:$M,redes!A6) -> 0
A7: 32893116 | B7: CLEBERSON DA SILVA RODRIGUES | C7: CAMPO GRANDE | F7: =IFERROR(VLOOKUP($A7,'319'!$B:$H,7,0),0) -> 0 | G7: =SUMIFS('12.326ana'!$C:$C,'12.326ana'!$M:$M,redes!A7) -> 0
A8: 32926146 | B8: ELISVALDO MARTINS DE MACEDO | C8: COSTA RICA | E8: ART PAES PANIFICADORA | F8: =IFERROR(VLOOKUP($A8,'319'!$B:$H,7,0),0) -> 0 | G8: =SUMIFS('12.326ana'!$C:$C,'12.326ana'!$M:$M,redes!A8) -> 0
A9: 33571120 | B9: ADRIANO APARECIDO GAMARRA (VEND 106) | C9: CAMPO GRANDE | E9: ADRIAN | F9: =IFERROR(VLOOKUP($A9,'319'!$B:$H,7,0),0) -> 0 | G9: =SUMIFS('12.326ana'!$C:$C,'12.326ana'!$M:$M,redes!A9) -> 0
A10: 34263348 | B10: DALVA MARTINS ZANDONADI | C10: CAMPO GRANDE | E10: MERCADO FLORES | F10: =IFERROR(VLOOKUP($A10,'319'!$B:$H,7,0),0) -> 0 | G10: =SUMIFS('12.326ana'!$C:$C,'12.326ana'!$M:$M,redes!A10) -> 0
A11: 37302396 | B11: ANTONIO MARCOS PEREIRA | C11: DOURADOS | E11: MERCADO ARCO IRIS | F11: =IFERROR(VLOOKUP($A11,'319'!$B:$H,7,0),0) -> 0 | G11: =SUMIFS('12.326ana'!$C:$C,'12.326ana'!$M:$M,redes!A11) -> 0
A12: 41223136 | B12: MARCELO JOSE DA SILVA | C12: CASSILANDIA | E12: PANF J.K | F12: =IFERROR(VLOOKUP($A12,'319'!$B:$H,7,0),0) -> 0 | G12: =SUMIFS('12.326ana'!$C:$C,'12.326ana'!$M:$M,redes!A12) -> 0
A13: 42116422 | B13: MARIA DAS DORES PINHEIRO DOMINGOS | C13: CAMPO GRANDE | E13: MERCADO MAIZA | F13: =IFERROR(VLOOKUP($A13,'319'!$B:$H,7,0),0) -> 0 | G13: =SUMIFS('12.326ana'!$C:$C,'12.326ana'!$M:$M,redes!A13) -> 0
A14: 48093513 | B14: JOSE HUMBERTO MACHADO MACEDO | C14: CAMPO GRANDE | E14: BIROSCA CONVENIENCIA | F14: =IFERROR(VLOOKUP($A14,'319'!$B:$H,7,0),0) -> 0 | G14: =SUMIFS('12.326ana'!$C:$C,'12.326ana'!$M:$M,redes!A14) -> 0
A15: 49871102 | B15: CLAUDIA FREITAS DE SOUZA | C15: CAMPO GRANDE | E15: MERCADO MORAES | F15: =IFERROR(VLOOKUP($A15,'319'!$B:$H,7,0),0) -> 0 | G15: =SUMIFS('12.326ana'!$C:$C,'12.326ana'!$M:$M,redes!A15) -> 0
A16: 62672118 | B16: HEMERSOM PRADO ELIAS | C16: APARECIDA DO TABOADO | E16: MINI MERCADO TABOADO | F16: =IFERROR(VLOOKUP($A16,'319'!$B:$H,7,0),0) -> 0 | G16: =SUMIFS('12.326ana'!$C:$C,'12.326ana'!$M:$M,redes!A16) -> 0
A17: 63064111 | B17: NILTON ARAUJO SILVA | C17: DOURADOS | E17: MERCADO VITORIA | F17: =IFERROR(VLOOKUP($A17,'319'!$B:$H,7,0),0) -> 0 | G17: =SUMIFS('12.326ana'!$C:$C,'12.326ana'!$M:$M,redes!A17) -> 0
A18: 63354110 | B18: KLEITON SAFFE DELMONTES | C18: CAMPO GRANDE | E18: MERCADO PAULISTA | F18: =IFERROR(VLOOKUP($A18,'319'!$B:$H,7,0),0) -> 0 | G18: =SUMIFS('12.326ana'!$C:$C,'12.326ana'!$M:$M,redes!A18) -> 0
A19: 63556170 | B19: MARCELO DOS SANTOS RIBEIRO | C19: DOURADOS | E19: MARCELO DOS SANTOS RIBEIRO | F19: =IFERROR(VLOOKUP($A19,'319'!$B:$H,7,0),0) -> 0 | G19: =SUMIFS('12.326ana'!$C:$C,'12.326ana'!$M:$M,redes!A19) -> 0
... A21: 64261158 | B21: JAIME DOS SANTOS | C21: CAMPO GRANDE | E21: LANCHONETE BAMBINA | F21: =IFERROR(VLOOKUP($A21,'319'!$B:$H,7,0),0) -> 0 | G21: =SUMIFS('12.326ana'!$C:$C,'12.326ana'!$M:$M,redes!A21) -> 0
A22: 71488103 | B22: CLEITON DA SILVA ANJOLIN | C22: DOURADOS | F22: =IFERROR(VLOOKUP($A22,'319'!$B:$H,7,0),0) -> 0 | G22: =SUMIFS('12.326ana'!$C:$C,'12.326ana'!$M:$M,redes!A22) -> 0
A23: 73799351 | B23: LEIDE DE ALENCAR KLEIN | C23: CAMPO GRANDE | E23: ESCOLA PADRE BLANDINO | F23: =IFERROR(VLOOKUP($A23,'319'!$B:$H,7,0),0) -> 0 | G23: =SUMIFS('12.326ana'!$C:$C,'12.326ana'!$M:$M,redes!A23) -> 0
A24: 77511174 | B24: ELIZANGELA COSTA PEIXOTO | C24: CAMPO GRANDE | E24: MERCEARIA ANACHE | F24: =IFERROR(VLOOKUP($A24,'319'!$B:$H,7,0),0) -> 0 | G24: =SUMIFS('12.326ana'!$C:$C,'12.326ana'!$M:$M,redes!A24) -> 0
A25: 81935170 | B25: DORIANE BENITES | C25: CAMPO GRANDE | E25: LAV AKY LAVANDERIA | F25: =IFERROR(VLOOKUP($A25,'319'!$B:$H,7,0),0) -> 0 | G25: =SUMIFS('12.326ana'!$C:$C,'12.326ana'!$M:$M,redes!A25) -> 0
A26: 82174164 | B26: SUZI MEIRE VITTORAZI | C26: CAMPO GRANDE | E26: SUZI MEIRE VITTORAZI | F26: =IFERROR(VLOOKUP($A26,'319'!$B:$H,7,0),0) -> 0 | G26: =SUMIFS('12.326ana'!$C:$C,'12.326ana'!$M:$M,redes!A26) -> 0
A27: 83890122 | B27: JOSE TIAGO DOS SANTOS | C27: NAVIRAI | E27: MRC IDEAL | F27: =IFERROR(VLOOKUP($A27,'319'!$B:$H,7,0),0) -> 0 | G27: =SUMIFS('12.326ana'!$C:$C,'12.326ana'!$M:$M,redes!A27) -> 0
A28: 90526155 | B28: ADRIANI ZIGLIOLI | C28: CAMPO GRANDE | F28: =IFERROR(VLOOKUP($A28,'319'!$B:$H,7,0),0) -> 0 | G28: =SUMIFS('12.326ana'!$C:$C,'12.326ana'!$M:$M,redes!A28) -> 0
A29: 92278140 | B29: WEBER BARCELOS PAULINO | C29: CASSILANDIA | E29: MEGA BEER | F29: =IFERROR(VLOOKUP($A29,'319'!$B:$H,7,0),0) -> 0 | G29: =SUMIFS('12.326ana'!$C:$C,'12.326ana'!$M:$M,redes!A29) -> 0
A30: 93906188 | B30: EDNA CONCEICAO DE OLIVEIRA | C30: CAMPO GRANDE | E30: PADARIA YULLIAYAME | F30: =IFERROR(VLOOKUP($A30,'319'!$B:$H,7,0),0) -> 0 | G30: =SUMIFS('12.326ana'!$C:$C,'12.326ana'!$M:$M,redes!A30) -> 0
A31: 93981120 | B31: EVANILSON SIGARINI SOARES | C31: CORUMBA | E31: EVANILSON SIGARINI SOARES | F31: =IFERROR(VLOOKUP($A31,'319'!$B:$H,7,0),0) -> 0 | G31: =SUMIFS('12.326ana'!$C:$C,'12.326ana'!$M:$M,redes!A31) -> 0
A32: 94980101 | B32: LUCIANE PEREIRA | C32: CAMPO GRANDE | E32: LUA CONVENIENCIA | F32: =IFERROR(VLOOKUP($A32,'319'!$B:$H,7,0),0) -> 0 | G32: =SUMIFS('12.326ana'!$C:$C,'12.326ana'!$M:$M,redes!A32) -> 0
A33: 96680121 | B33: FERNANDO WEINERT | C33: CAMPO GRANDE | E33: FERNANDO | F33: =IFERROR(VLOOKUP($A33,'319'!$B:$H,7,0),0) -> 0 | G33: =SUMIFS('12.326ana'!$C:$C,'12.326ana'!$M:$M,redes!A33) -> 0
A34: 97030120 | B34: ROGERIO ROBEIRO AMORIM | C34: CAMPO GRANDE | E34: PANIF HAWAY | F34: =IFERROR(VLOOKUP($A34,'319'!$B:$H,7,0),0) -> 0 | G34: =SUMIFS('12.326ana'!$C:$C,'12.326ana'!$M:$M,redes!A34) -> 0
A35: 104112166 | B35: ZENAIDE MARTINS DA SILVA | C35: DOURADOS | E35: MERCEARIA MARTIANO | F35: =IFERROR(VLOOKUP($A35,'319'!$B:$H,7,0),0) -> 0 | G35: =SUMIFS('12.326ana'!$C:$C,'12.326ana'!$M:$M,redes!A35) -> 0
A36: 108857654 | B36: LORETE TAWIL | C36: CAMPO GRANDE | E36: HORA DO LANCHE | F36: =IFERROR(VLOOKUP($A36,'319'!$B:$H,7,0),0) -> 0 | G36: =SUMIFS('12.326ana'!$C:$C,'12.326ana'!$M:$M,redes!A36) -> 0
A37: 109531167 | B37: CLEOMAR MAIA | C37: CAMPO GRANDE | E37: CLEOMAR DEPOSITO | F37: =IFERROR(VLOOKUP($A37,'319'!$B:$H,7,0),0) -> 0 | G37: =SUMIFS('12.326ana'!$C:$C,'12.326ana'!$M:$M,redes!A37) -> 0
A38: 109830156 | B38: CLEONICE R DE LIMA | C38: CAMPO GRANDE | E38: MERCEARIA VIEIRA | F38: =IFERROR(VLOOKUP($A38,'319'!$B:$H,7,0),0) -> 0 | G38: =SUMIFS('12.326ana'!$C:$C,'12.326ana'!$M:$M,redes!A38) -> 0
A39: 109917197 | B39: ROSANGELA FREIRE DE CASTRO | C39: ANASTACIO | E39: MERCEARIA CONVENIENCIA DA NEGA | F39: =IFERROR(VLOOKUP($A39,'319'!$B:$H,7,0),0) -> 0 | G39: =SUMIFS('12.326ana'!$C:$C,'12.326ana'!$M:$M,redes!A39) -> 0
A40: 120380161 | B40: ALEXANDRA DOS SANTOS RODRIGUES | C40: CAMPO GRANDE | E40: ALEXANDRA DOS SANTOS RODRIGUES | F40: =IFERROR(VLOOKUP($A40,'319'!$B:$H,7,0),0) -> 0 | G40: =SUMIFS('12.326ana'!$C:$C,'12.326ana'!$M:$M,redes!A40) -> 0
... A42: 121313182 | B42: EMERSON DIAS DOS SANTOS | C42: CAMPO GRANDE | E42: MERCADO DIAS | F42: =IFERROR(VLOOKUP($A42,'319'!$B:$H,7,0),0) -> 0 | G42: =SUMIFS('12.326ana'!$C:$C,'12.326ana'!$M:$M,redes!A42) -> 0
A43: 121434133 | B43: NEREIDE BRAULIO NOVAES | C43: CAMPO GRANDE | F43: =IFERROR(VLOOKUP($A43,'319'!$B:$H,7,0),0) -> 0 | G43: =SUMIFS('12.326ana'!$C:$C,'12.326ana'!$M:$M,redes!A43) -> 0
A44: 123147140 | B44: LESSIO DOS SANTOS ME | C44: CAMPO GRANDE | E44: MERCADO E ACOUGUE BOIADEIRO S | F44: =IFERROR(VLOOKUP($A44,'319'!$B:$H,7,0),0) -> 0 | G44: =SUMIFS('12.326ana'!$C:$C,'12.326ana'!$M:$M,redes!A44) -> 0
A45: 124185100 | B45: MILENE DE OLIVEIRA SPESSATTO | C45: DOURADOS | E45: AUTO POSTO LILIAM | F45: =IFERROR(VLOOKUP($A45,'319'!$B:$H,7,0),0) -> 0 | G45: =SUMIFS('12.326ana'!$C:$C,'12.326ana'!$M:$M,redes!A45) -> 0
A46: 128209119 | B46: TIAGO RIBEIRO DE MORAES | C46: RIO BRILHANTE | E46: MERCADO MEG BOM | F46: =IFERROR(VLOOKUP($A46,'319'!$B:$H,7,0),0) -> 0 | G46: =SUMIFS('12.326ana'!$C:$C,'12.326ana'!$M:$M,redes!A46) -> 0
A47: 128726105 | B47: DOUGLAS MAGNO ESPINDOLO DELGADO | C47: CAMPO GRANDE | E47: TAQUARAS BAR | F47: =IFERROR(VLOOKUP($A47,'319'!$B:$H,7,0),0) -> 0 | G47: =SUMIFS('12.326ana'!$C:$C,'12.326ana'!$M:$M,redes!A47) -> 0
A48: 131450107 | B48: HELLEN CRISTIE DE ARRUDA VIEDES | C48: CAMPO GRANDE | E48: CONVENIENCIA CEBOLINHA | F48: =IFERROR(VLOOKUP($A48,'319'!$B:$H,7,0),0) -> 0 | G48: =SUMIFS('12.326ana'!$C:$C,'12.326ana'!$M:$M,redes!A48) -> 0
A49: 132280132 | B49: PAULO GEOVANI TEIXEIRA NETTO | C49: DOURADOS | E49: CONVENIENCIA E PADARIA | F49: =IFERROR(VLOOKUP($A49,'319'!$B:$H,7,0),0) -> 0 | G49: =SUMIFS('12.326ana'!$C:$C,'12.326ana'!$M:$M,redes!A49) -> 0
A50: 134729170 | B50: SUZANA FAGUNDES DOS SANTOS | C50: SANTA RITA DO PARDO | E50: CABECINHAS BAR | F50: =IFERROR(VLOOKUP($A50,'319'!$B:$H,7,0),0) -> 0 | G50: =SUMIFS('12.326ana'!$C:$C,'12.326ana'!$M:$M,redes!A50) -> 0
A51: 134749103 | B51: ADRIANA AMARILLA CRISTALDO | C51: CAMPO GRANDE | E51: SANTA MARIA | F51: =IFERROR(VLOOKUP($A51,'319'!$B:$H,7,0),0) -> 0 | G51: =SUMIFS('12.326ana'!$C:$C,'12.326ana'!$M:$M,redes!A51) -> 0
A52: 134911130 | B52: SANDRA REGINA SARTORIO FERRAZ | C52: COXIM | E52: SANDRA REGINA SARTORIO FERRAZ | F52: =IFERROR(VLOOKUP($A52,'319'!$B:$H,7,0),0) -> 0 | G52: =SUMIFS('12.326ana'!$C:$C,'12.326ana'!$M:$M,redes!A52) -> 0
A53: 143275119 | B53: MILENE DIAS DE SOUZA | C53: CAMPO GRANDE | E53: MERCADO BOM PRECO | F53: =IFERROR(VLOOKUP($A53,'319'!$B:$H,7,0),0) -> 0 | G53: =SUMIFS('12.326ana'!$C:$C,'12.326ana'!$M:$M,redes!A53) -> 0
A54: 143335111 | B54: SIDNEY PRESTES DE MACEDO | C54: CAMPO GRANDE | E54: MERCADO VANDAO | F54: =IFERROR(VLOOKUP($A54,'319'!$B:$H,7,0),0) -> 0 | G54: =SUMIFS('12.326ana'!$C:$C,'12.326ana'!$M:$M,redes!A54) -> 0
A55: 145252167 | B55: RENATA DA SILVA CRUZ | C55: CAMPO GRANDE | E55: CORUJINHA CON | F55: =IFERROR(VLOOKUP($A55,'319'!$B:$H,7,0),0) -> 0 | G55: =SUMIFS('12.326ana'!$C:$C,'12.326ana'!$M:$M,redes!A55) -> 0
... A76: 204388180 | B76: RITA SOUZA DE AMORIM OLIVEIRA | C76: CAMPO GRANDE | E76: MERCADO OLIVEIRA | F76: =IFERROR(VLOOKUP($A76,'319'!$B:$H,7,0),0) -> 0 | G76: =SUMIFS('12.326ana'!$C:$C,'12.326ana'!$M:$M,redes!A76) -> 0
A77: 206209185 | B77: RODRIGO MIRANDA MONTEIRO | C77: RIO VERDE DE MATO GROSSO | F77: =IFERROR(VLOOKUP($A77,'319'!$B:$H,7,0),0) -> 0 | G77: =SUMIFS('12.326ana'!$C:$C,'12.326ana'!$M:$M,redes!A77) -> 0
A78: 214538109 | B78: APARECIDA SALETE DELISE DE AQUINO | C78: CAMPO GRANDE | E78: MERCEARIA SAO JOAO BATISTA | F78: =IFERROR(VLOOKUP($A78,'319'!$B:$H,7,0),0) -> 0 | G78: =SUMIFS('12.326ana'!$C:$C,'12.326ana'!$M:$M,redes!A78) -> 0
A79: 216219183 | B79: CLAUDEMIR DE FREITAS BERNANDO | C79: PARANAIBA | E79: MINI MERCADO SKINAO | F79: =IFERROR(VLOOKUP($A79,'319'!$B:$H,7,0),0) -> 0 | G79: =SUMIFS('12.326ana'!$C:$C,'12.326ana'!$M:$M,redes!A79) -> 0
A80: 218782187 | B80: GERALDO BARBOSA SOLARI | C80: CAMPO GRANDE | F80: =IFERROR(VLOOKUP($A80,'319'!$B:$H,7,0),0) -> 0 | G80: =SUMIFS('12.326ana'!$C:$C,'12.326ana'!$M:$M,redes!A80) -> 0
A81: 232477116 | B81: ROSA MENDES SANTIAGO | C81: CAMAPUA | E81: PANIF JL | F81: =IFERROR(VLOOKUP($A81,'319'!$B:$H,7,0),0) -> 0 | G81: =SUMIFS('12.326ana'!$C:$C,'12.326ana'!$M:$M,redes!A81) -> 0
A82: 236097881 | B82: APARECIDO GUEDES DE SOUZA | C82: CAMPO GRANDE | E82: APARECIDO GUEDES DE SOUZA | F82: =IFERROR(VLOOKUP($A82,'319'!$B:$H,7,0),0) -> 0 | G82: =SUMIFS('12.326ana'!$C:$C,'12.326ana'!$M:$M,redes!A82) -> 0
A83: 236413120 | B83: LAURA SOLANGE | C83: APARECIDA DO TABOADO | E83: SM AGUA NOVA | F83: =IFERROR(VLOOKUP($A83,'319'!$B:$H,7,0),0) -> 0 | G83: =SUMIFS('12.326ana'!$C:$C,'12.326ana'!$M:$M,redes!A83) -> 0
A84: 239462106 | B84: MERCADO E ACOUGUE JS | C84: CAMPO GRANDE | E84: MERCADO ACOUGUE JS | F84: =IFERROR(VLOOKUP($A84,'319'!$B:$H,7,0),0) -> 0 | G84: =SUMIFS('12.326ana'!$C:$C,'12.326ana'!$M:$M,redes!A84) -> 0
A85: 241108179 | B85: LAURENTINO FERREIRA DE OL NETO | C85: CAMPO GRANDE | E85: PSICULTURA LANCH CACHOEIRA | F85: =IFERROR(VLOOKUP($A85,'319'!$B:$H,7,0),0) -> 0 | G85: =SUMIFS('12.326ana'!$C:$C,'12.326ana'!$M:$M,redes!A85) -> 0
A86: 244629188 | B86: ALDOIR ANTONIO BOLLER | C86: IGUATEMI | E86: CANTINA RODOVIARIA | F86: =IFERROR(VLOOKUP($A86,'319'!$B:$H,7,0),0) -> 0 | G86: =SUMIFS('12.326ana'!$C:$C,'12.326ana'!$M:$M,redes!A86) -> 0
A87: 245048154 | B87: DIANA PRADO DA SILVA | C87: CAMPO GRANDE | E87: PANF CABREUVA | F87: =IFERROR(VLOOKUP($A87,'319'!$B:$H,7,0),0) -> 0 | G87: =SUMIFS('12.326ana'!$C:$C,'12.326ana'!$M:$M,redes!A87) -> 0
A88: 249704170 | B88: VALDECI FRANCA DE SOUZA | C88: CAMPO GRANDE | E88: MERCEARIA CW | F88: =IFERROR(VLOOKUP($A88,'319'!$B:$H,7,0),0) -> 0 | G88: =SUMIFS('12.326ana'!$C:$C,'12.326ana'!$M:$M,redes!A88) -> 0
A89: 255535180 | B89: TANIA GOMES FERREIRA | C89: CAMPO GRANDE | E89: PANIF 7 COPAS | F89: =IFERROR(VLOOKUP($A89,'319'!$B:$H,7,0),0) -> 0 | G89: =SUMIFS('12.326ana'!$C:$C,'12.326ana'!$M:$M,redes!A89) -> 0
A90: 258099119 | B90: SELMA PEREIRA GUIMARAES | C90: CAMPO GRANDE | E90: MERCADO MANANCIAL | F90: =IFERROR(VLOOKUP($A90,'319'!$B:$H,7,0),0) -> 0 | G90: =SUMIFS('12.326ana'!$C:$C,'12.326ana'!$M:$M,redes!A90) -> 0
A91: 258420138 | B91: SILVIA HELENA PEREIRA DOS SANTOS | C91: CAMPO GRANDE | E91: SILVINHA | F91: =IFERROR(VLOOKUP($A91,'319'!$B:$H,7,0),0) -> 0 | G91: =SUMIFS('12.326ana'!$C:$C,'12.326ana'!$M:$M,redes!A91) -> 0
A92: 259189154 | B92: RICARDO DOS SANTOS FERREIRA | C92: CAMPO GRANDE | E92: SAO JOAO MERCEARIA | F92: =IFERROR(VLOOKUP($A92,'319'!$B:$H,7,0),0) -> 0 | G92: =SUMIFS('12.326ana'!$C:$C,'12.326ana'!$M:$M,redes!A92) -> 0
... A95: 269848142 | B95: LARI L PAS DO REAL | C95: TRES LAGOAS | E95: PANIF TRES LAGOAS | F95: =IFERROR(VLOOKUP($A95,'319'!$B:$H,7,0),0) -> 0 | G95: =SUMIFS('12.326ana'!$C:$C,'12.326ana'!$M:$M,redes!A95) -> 0
A96: 280872160 | B96: MARILCE DOS SANTOS | C96: PORTO MURTINHO | F96: =IFERROR(VLOOKUP($A96,'319'!$B:$H,7,0),0) -> 0 | G96: =SUMIFS('12.326ana'!$C:$C,'12.326ana'!$M:$M,redes!A96) -> 0
A97: 288806174 | B97: INACIO ANTONIO DE CARVALHO JUNIOR | C97: CAMPO GRANDE | E97: GIBA CONVENIENCIA | F97: =IFERROR(VLOOKUP($A97,'319'!$B:$H,7,0),0) -> 0 | G97: =SUMIFS('12.326ana'!$C:$C,'12.326ana'!$M:$M,redes!A97) -> 0
A98: 312003110 | B98: EDVALDO JUNIOR DE QUEIROZ | C98: CAMPO GRANDE | E98: MERCADO GANGURU | F98: =IFERROR(VLOOKUP($A98,'319'!$B:$H,7,0),0) -> 0 | G98: =SUMIFS('12.326ana'!$C:$C,'12.326ana'!$M:$M,redes!A98) -> 0
A99: 313933146 | B99: EDINEI APOLONIO BARBOSA | C99: DOURADOS | E99: CONV E MERCEARIA BARBOSA | F99: =IFERROR(VLOOKUP($A99,'319'!$B:$H,7,0),0) -> 0 | G99: =SUMIFS('12.326ana'!$C:$C,'12.326ana'!$M:$M,redes!A99) -> 0
A100: 314727108 | B100: VALMIR DE JESUS LOPES | C100: CAMPO GRANDE | E100: CONVENIENCIA DO CARECA | F100: =IFERROR(VLOOKUP($A100,'319'!$B:$H,7,0),0) -> 0 | G100: =SUMIFS('12.326ana'!$C:$C,'12.326ana'!$M:$M,redes!A100) -> 0
A101: 314804110 | B101: WAGNER APARECIDO MOURA | C101: CAMPO GRANDE | E101: MERCEARIA E SACOLAO | F101: =IFERROR(VLOOKUP($A101,'319'!$B:$H,7,0),0) -> 0 | G101: =SUMIFS('12.326ana'!$C:$C,'12.326ana'!$M:$M,redes!A101) -> 0
A102: 314866140 | B102: SONIA LOPES DUTRA | C102: TACURU | E102: MINI MERCADO DUTRA | F102: =IFERROR(VLOOKUP($A102,'319'!$B:$H,7,0),0) -> 0 | G102: =SUMIFS('12.326ana'!$C:$C,'12.326ana'!$M:$M,redes!A102) -> 0
A103: 315195800 | B103: BENTO FERREIRA DE LEMOS | C103: CAMPO GRANDE | E103: MERCEARIA FERREIRA | F103: =IFERROR(VLOOKUP($A103,'319'!$B:$H,7,0),0) -> 0 | G103: =SUMIFS('12.326ana'!$C:$C,'12.326ana'!$M:$M,redes!A103) -> 0
A104: 323295126 | B104: CAMILA DUTRA CARDOSO | C104: CAMPO GRANDE | E104: PANIF ALIANCA | F104: =IFERROR(VLOOKUP($A104,'319'!$B:$H,7,0),0) -> 0 | G104: =SUMIFS('12.326ana'!$C:$C,'12.326ana'!$M:$M,redes!A104) -> 0
A105: 328145181 | B105: ELIANE DOS SANTOS GAUTO | C105: CAMPO GRANDE | E105: MERCADO AQUARIOS | F105: =IFERROR(VLOOKUP($A105,'319'!$B:$H,7,0),0) -> 0 | G105: =SUMIFS('12.326ana'!$C:$C,'12.326ana'!$M:$M,redes!A105) -> 0
A106: 330780174 | B106: ANA CLAUDIA OLIVEIRA RAFAEL | C106: CAMPO GRANDE | E106: MERCEARIA RAFAEL | F106: =IFERROR(VLOOKUP($A106,'319'!$B:$H,7,0),0) -> 0 | G106: =SUMIFS('12.326ana'!$C:$C,'12.326ana'!$M:$M,redes!A106) -> 0
A107: 337003114 | B107: SOLANGE LAURINDO DE LIMA | C107: CAMPO GRANDE | E107: MERCEARIA E LOJA ALTERNATIVA | F107: =IFERROR(VLOOKUP($A107,'319'!$B:$H,7,0),0) -> 0 | G107: =SUMIFS('12.326ana'!$C:$C,'12.326ana'!$M:$M,redes!A107) -> 0
A108: 338546103 | B108: ANGELICA MARTINS CABREIRA | C108: CAMPO GRANDE | E108: COVENIENCIA KAROLINA | F108: =IFERROR(VLOOKUP($A108,'319'!$B:$H,7,0),0) -> 0 | G108: =SUMIFS('12.326ana'!$C:$C,'12.326ana'!$M:$M,redes!A108) -> 0
... A119: 393852130 | B119: RICKSON AYNORI BENEDITO LIMA | C119: CAMPO GRANDE | E119: MERCADO REAL | F119: =IFERROR(VLOOKUP($A119,'319'!$B:$H,7,0),0) -> 0 | G119: =SUMIFS('12.326ana'!$C:$C,'12.326ana'!$M:$M,redes!A119) -> 0
A120: 400027135 | B120: ANTONIO DA SILVA ARAUJO | C120: IVINHEMA | F120: =IFERROR(VLOOKUP($A120,'319'!$B:$H,7,0),0) -> 0 | G120: =SUMIFS('12.326ana'!$C:$C,'12.326ana'!$M:$M,redes!A120) -> 0
A121: 407319107 | B121: TATIANA FRANCA | C121: CAMPO GRANDE | F121: =IFERROR(VLOOKUP($A121,'319'!$B:$H,7,0),0) -> 0 | G121: =SUMIFS('12.326ana'!$C:$C,'12.326ana'!$M:$M,redes!A121) -> 0
A122: 413698157 | B122: APARECIDA FRAGATO DOS SANTOS | C122: CAMPO GRANDE | E122: MERCEARIA TUIUIU | F122: =IFERROR(VLOOKUP($A122,'319'!$B:$H,7,0),0) -> 0 | G122: =SUMIFS('12.326ana'!$C:$C,'12.326ana'!$M:$M,redes!A122) -> 0
A123: 414620178 | B123: GIL PASSIFICO TOGNINI | C123: CAMPO GRANDE | E123: AVENIDA CONVENIENCIA | F123: =IFERROR(VLOOKUP($A123,'319'!$B:$H,7,0),0) -> 0 | G123: =SUMIFS('12.326ana'!$C:$C,'12.326ana'!$M:$M,redes!A123) -> 0
A124: 415827132 | B124: EZEQUIEL ANTONIO ROSATO | C124: JARDIM | E124: CONVEN LA | F124: =IFERROR(VLOOKUP($A124,'319'!$B:$H,7,0),0) -> 0 | G124: =SUMIFS('12.326ana'!$C:$C,'12.326ana'!$M:$M,redes!A124) -> 0
A125: 419119892 | B125: LAURO FERREIRA BARBOSA | C125: CAMPO GRANDE | E125: LOJA DO LAURO | F125: =IFERROR(VLOOKUP($A125,'319'!$B:$H,7,0),0) -> 0 | G125: =SUMIFS('12.326ana'!$C:$C,'12.326ana'!$M:$M,redes!A125) -> 0
A126: 419669884 | B126: PEDRO DE SOUZA OLIVEIRA | C126: DOURADOS | E126: MERCEARIA OLIVEIRA | F126: =IFERROR(VLOOKUP($A126,'319'!$B:$H,7,0),0) -> 0 | G126: =SUMIFS('12.326ana'!$C:$C,'12.326ana'!$M:$M,redes!A126) -> 0
A127: 421768169 | B127: MARIA APARECIDA DA SILVA | C127: NOVA ALVORADA DO SUL | E127: SM VERDURAO JVM | F127: =IFERROR(VLOOKUP($A127,'319'!$B:$H,7,0),0) -> 0 | G127: =SUMIFS('12.326ana'!$C:$C,'12.326ana'!$M:$M,redes!A127) -> 0
A128: 421993103 | B128: DOUGLAS SOUZA DA SILVA | C128: CAMPO GRANDE | F128: =IFERROR(VLOOKUP($A128,'319'!$B:$H,7,0),0) -> 0 | G128: =SUMIFS('12.326ana'!$C:$C,'12.326ana'!$M:$M,redes!A128) -> 0
A129: 431233179 | B129: DIEGO DE OLIVEIRA PEREIRA (REP 107) | C129: CAMPO GRANDE | E129: PAIA SECA | F129: =IFERROR(VLOOKUP($A129,'319'!$B:$H,7,0),0) -> 0 | G129: =SUMIFS('12.326ana'!$C:$C,'12.326ana'!$M:$M,redes!A129) -> 0
A130: 433733802 | B130: MARIA APARECIDA BARBOSA | C130: DOURADOS | E130: CANTINA DA MACE | F130: =IFERROR(VLOOKUP($A130,'319'!$B:$H,7,0),0) -> 0 | G130: =SUMIFS('12.326ana'!$C:$C,'12.326ana'!$M:$M,redes!A130) -> 0
A131: 436878143 | B131: MARCELLO DELFIM DE BARROS GONZAGA | C131: CAMPO GRANDE | E131: MARCELLO DELFIM DE BARROS GONZAGA | F131: =IFERROR(VLOOKUP($A131,'319'!$B:$H,7,0),0) -> 0 | G131: =SUMIFS('12.326ana'!$C:$C,'12.326ana'!$M:$M,redes!A131) -> 0
A132: 464345189 | B132: WALDECY DE OLIVEIRA LUIZ | C132: CAMPO GRANDE | E132: WAL CONVENIENCIA | F132: =IFERROR(VLOOKUP($A132,'319'!$B:$H,7,0),0) -> 0 | G132: =SUMIFS('12.326ana'!$C:$C,'12.326ana'!$M:$M,redes!A132) -> 0
A133: 466497199 | B133: SIMONE BATISTA REIS | C133: CAMPO GRANDE | E133: MERCADO SIVAL | F133: =IFERROR(VLOOKUP($A133,'319'!$B:$H,7,0),0) -> 0 | G133: =SUMIFS('12.326ana'!$C:$C,'12.326ana'!$M:$M,redes!A133) -> 0
A134: 482849983 | B134: ELIANE DE JESUS GASPARETO | C134: MUNDO NOVO | E134: FRUTAO | F134: =IFERROR(VLOOKUP($A134,'319'!$B:$H,7,0),0) -> 0 | G134: =SUMIFS('12.326ana'!$C:$C,'12.326ana'!$M:$M,redes!A134) -> 0
...

Sheet Equipe
A1: COD | B1: NOME | C1: COORD | D1: NOME COORD | E1: EQUIPE
A2: 100 | B2: BALCÃO | C2: 998 | D2: GERENCIA | E2: 1
A3: 130 | B3: CLT - JOSE LUCA | C3: 906 | D3: THIAGO - MC.KA | E3: 6
A4: 135 | B4: CLT - TALITA GO | C4: 906 | D4: THIAGO - MC.KA | E4: 6
A5: 211 | B5: PJ - PAULA REGI | C5: 906 | D5: THIAGO - MC.KA | E5: 1
A6: 301 | B6: CLT - MAX DOS S | C6: 906 | D6: THIAGO - MC.KA | E6: 1
A7: 507 | B7: CLT - CLAUDIMIR | C7: 906 | D7: THIAGO - MC.KA | E7: 1
A8: 702 | B8: CLT - RENATA MA | C8: 906 | D8: THIAGO - MC.KA | E8: 1
A9: 703 | B9: PJ - FERNANDO A | C9: 902 | D9: CLAUDIO - VAREJ | E9: 1
A10: 704 | B10: CLT - GILBERTO | C10: 910 | D10: JONATAS - VAREJ | E10: 1
A11: 705 | B11: CLT - TATIANA M | C11: 910 | D11: JONATAS - VAREJ | E11: 1
A12: 706 | B12: PJ - NILVANIA L | C12: 902 | D12: CLAUDIO - VAREJ | E12: 1
A13: 707 | B13: CLT - LORENA DA | C13: 910 | D13: JONATAS - VAREJ | E13: 1
... A27: 800 | B27: CLT - CRISTIAN | C27: 902 | D27: CLAUDIO - VAREJ | E27: 6
A28: 759 | B28: BRUNO DE SOUZA NUNES | C28: 904 | D28: DANIELLE CORTES MORAIS
